[
{
	"PbTyp": "WASSER",
	"PbNahmeDatum": "02.01.2013",
	"Parameter": "Atrazin",
	"Einheiten": "µg/L",
	"Wert Text": 0.013,
	"CAS": "1912-24-9",
	"Gruppe": "Pestizide",
	"DauerPN_h": 24,
	"Q_m3_s": 1471.43,
	"M_in_mg_L": 13,
	"Tage": 1,
	"Datum_Start": "01.01.2013",
	"mg_pro_24h": 13
},
{
	"PbTyp": "WASSER",
	"PbNahmeDatum": "02.01.2013",
	"Parameter": "Atrazin",
	"Einheiten": "µg/L",
	"Wert Text": 0.005,
	"CAS": "1912-24-9",
	"Gruppe": "Pestizide",
	"DauerPN_h": 24,
	"Q_m3_s": 1471.43,
	"M_in_mg_L": 5,
	"Tage": 1,
	"Datum_Start": "01.01.2013",
	"mg_pro_24h": 5
},
{
	"PbTyp": "WASSER",
	"PbNahmeDatum": "03.01.2013",
	"Parameter": "Atrazin",
	"Einheiten": "µg/L",
	"Wert Text": 0.013,
	"CAS": "1912-24-9",
	"Gruppe": "Pestizide",
	"DauerPN_h": 24,
	"Q_m3_s": 1426.93,
	"M_in_mg_L": 13,
	"Tage": 1,
	"Datum_Start": "02.01.2013",
	"mg_pro_24h": 13
},
{
	"PbTyp": "WASSER",
	"PbNahmeDatum": "03.01.2013",
	"Parameter": "Atrazin",
	"Einheiten": "µg/L",
	"Wert Text": 0.005,
	"CAS": "1912-24-9",
	"Gruppe": "Pestizide",
	"DauerPN_h": 24,
	"Q_m3_s": 1426.93,
	"M_in_mg_L": 5,
	"Tage": 1,
	"Datum_Start": "02.01.2013",
	"mg_pro_24h": 5
},
{
	"PbTyp": "WASSER",
	"PbNahmeDatum": "04.01.2013",
	"Parameter": "Atrazin",
	"Einheiten": "µg/L",
	"Wert Text": 0.013,
	"CAS": "1912-24-9",
	"Gruppe": "Pestizide",
	"DauerPN_h": 24,
	"Q_m3_s": 1364.7,
	"M_in_mg_L": 13,
	"Tage": 1,
	"Datum_Start": "03.01.2013",
	"mg_pro_24h": 13
},
{
	"PbTyp": "WASSER",
	"PbNahmeDatum": "04.01.2013",
	"Parameter": "Atrazin",
	"Einheiten": "µg/L",
	"Wert Text": 0.005,
	"CAS": "1912-24-9",
	"Gruppe": "Pestizide",
	"DauerPN_h": 24,
	"Q_m3_s": 1364.7,
	"M_in_mg_L": 5,
	"Tage": 1,
	"Datum_Start": "03.01.2013",
	"mg_pro_24h": 5
},
{
	"PbTyp": "WASSER",
	"PbNahmeDatum": "05.01.2013",
	"Parameter": "Atrazin",
	"Einheiten": "µg/L",
	"Wert Text": 0.012,
	"CAS": "1912-24-9",
	"Gruppe": "Pestizide",
	"DauerPN_h": 24,
	"Q_m3_s": 1269.22,
	"M_in_mg_L": 12,
	"Tage": 1,
	"Datum_Start": "04.01.2013",
	"mg_pro_24h": 12
},
{
	"PbTyp": "WASSER",
	"PbNahmeDatum": "06.01.2013",
	"Parameter": "Atrazin",
	"Einheiten": "µg/L",
	"Wert Text": 0.012,
	"CAS": "1912-24-9",
	"Gruppe": "Pestizide",
	"DauerPN_h": 24,
	"Q_m3_s": 1258.04,
	"M_in_mg_L": 12,
	"Tage": 1,
	"Datum_Start": "05.01.2013",
	"mg_pro_24h": 12
},
{
	"PbTyp": "WASSER",
	"PbNahmeDatum": "06.01.2013",
	"Parameter": "Atrazin",
	"Einheiten": "µg/L",
	"Wert Text": 0.006,
	"CAS": "1912-24-9",
	"Gruppe": "Pestizide",
	"DauerPN_h": 24,
	"Q_m3_s": 1258.04,
	"M_in_mg_L": 6,
	"Tage": 1,
	"Datum_Start": "05.01.2013",
	"mg_pro_24h": 6
},
{
	"PbTyp": "WASSER",
	"PbNahmeDatum": "07.01.2013",
	"Parameter": "Atrazin",
	"Einheiten": "µg/L",
	"Wert Text": 0.012,
	"CAS": "1912-24-9",
	"Gruppe": "Pestizide",
	"DauerPN_h": 24,
	"Q_m3_s": 1233.43,
	"M_in_mg_L": 12,
	"Tage": 1,
	"Datum_Start": "06.01.2013",
	"mg_pro_24h": 12
},
{
	"PbTyp": "WASSER",
	"PbNahmeDatum": "08.01.2013",
	"Parameter": "Atrazin",
	"Einheiten": "µg/L",
	"Wert Text": 0.013,
	"CAS": "1912-24-9",
	"Gruppe": "Pestizide",
	"DauerPN_h": 24,
	"Q_m3_s": 1204.79,
	"M_in_mg_L": 13,
	"Tage": 1,
	"Datum_Start": "07.01.2013",
	"mg_pro_24h": 13
},
{
	"PbTyp": "WASSER",
	"PbNahmeDatum": "08.01.2013",
	"Parameter": "Atrazin",
	"Einheiten": "µg/L",
	"Wert Text": 0.005,
	"CAS": "1912-24-9",
	"Gruppe": "Pestizide",
	"DauerPN_h": 24,
	"Q_m3_s": 1204.79,
	"M_in_mg_L": 5,
	"Tage": 1,
	"Datum_Start": "07.01.2013",
	"mg_pro_24h": 5
},
{
	"PbTyp": "WASSER",
	"PbNahmeDatum": "09.01.2013",
	"Parameter": "Atrazin",
	"Einheiten": "µg/L",
	"Wert Text": 0.013,
	"CAS": "1912-24-9",
	"Gruppe": "Pestizide",
	"DauerPN_h": 24,
	"Q_m3_s": 1165.37,
	"M_in_mg_L": 13,
	"Tage": 1,
	"Datum_Start": "08.01.2013",
	"mg_pro_24h": 13
},
{
	"PbTyp": "WASSER",
	"PbNahmeDatum": "09.01.2013",
	"Parameter": "Atrazin",
	"Einheiten": "µg/L",
	"Wert Text": 0.006,
	"CAS": "1912-24-9",
	"Gruppe": "Pestizide",
	"DauerPN_h": 24,
	"Q_m3_s": 1165.37,
	"M_in_mg_L": 6,
	"Tage": 1,
	"Datum_Start": "08.01.2013",
	"mg_pro_24h": 6
},
{
	"PbTyp": "WASSER",
	"PbNahmeDatum": "10.01.2013",
	"Parameter": "Atrazin",
	"Einheiten": "µg/L",
	"Wert Text": 0.013,
	"CAS": "1912-24-9",
	"Gruppe": "Pestizide",
	"DauerPN_h": 24,
	"Q_m3_s": 1144.62,
	"M_in_mg_L": 13,
	"Tage": 1,
	"Datum_Start": "09.01.2013",
	"mg_pro_24h": 13
},
{
	"PbTyp": "WASSER",
	"PbNahmeDatum": "10.01.2013",
	"Parameter": "Atrazin",
	"Einheiten": "µg/L",
	"Wert Text": 0.006,
	"CAS": "1912-24-9",
	"Gruppe": "Pestizide",
	"DauerPN_h": 24,
	"Q_m3_s": 1144.62,
	"M_in_mg_L": 6,
	"Tage": 1,
	"Datum_Start": "09.01.2013",
	"mg_pro_24h": 6
},
{
	"PbTyp": "WASSER",
	"PbNahmeDatum": "11.01.2013",
	"Parameter": "Atrazin",
	"Einheiten": "µg/L",
	"Wert Text": 0.013,
	"CAS": "1912-24-9",
	"Gruppe": "Pestizide",
	"DauerPN_h": 24,
	"Q_m3_s": 1148.82,
	"M_in_mg_L": 13,
	"Tage": 1,
	"Datum_Start": "10.01.2013",
	"mg_pro_24h": 13
},
{
	"PbTyp": "WASSER",
	"PbNahmeDatum": "12.01.2013",
	"Parameter": "Atrazin",
	"Einheiten": "µg/L",
	"Wert Text": 0.014,
	"CAS": "1912-24-9",
	"Gruppe": "Pestizide",
	"DauerPN_h": 24,
	"Q_m3_s": 1282.29,
	"M_in_mg_L": 14,
	"Tage": 1,
	"Datum_Start": "11.01.2013",
	"mg_pro_24h": 14
},
{
	"PbTyp": "WASSER",
	"PbNahmeDatum": "13.01.2013",
	"Parameter": "Atrazin",
	"Einheiten": "µg/L",
	"Wert Text": 0.013,
	"CAS": "1912-24-9",
	"Gruppe": "Pestizide",
	"DauerPN_h": 24,
	"Q_m3_s": 1138.11,
	"M_in_mg_L": 13,
	"Tage": 1,
	"Datum_Start": "12.01.2013",
	"mg_pro_24h": 13
},
{
	"PbTyp": "WASSER",
	"PbNahmeDatum": "13.01.2013",
	"Parameter": "Atrazin",
	"Einheiten": "µg/L",
	"Wert Text": 0.005,
	"CAS": "1912-24-9",
	"Gruppe": "Pestizide",
	"DauerPN_h": 24,
	"Q_m3_s": 1138.11,
	"M_in_mg_L": 5,
	"Tage": 1,
	"Datum_Start": "12.01.2013",
	"mg_pro_24h": 5
},
{
	"PbTyp": "WASSER",
	"PbNahmeDatum": "14.01.2013",
	"Parameter": "Atrazin",
	"Einheiten": "µg/L",
	"Wert Text": 0.013,
	"CAS": "1912-24-9",
	"Gruppe": "Pestizide",
	"DauerPN_h": 24,
	"Q_m3_s": 1060.71,
	"M_in_mg_L": 13,
	"Tage": 1,
	"Datum_Start": "13.01.2013",
	"mg_pro_24h": 13
},
{
	"PbTyp": "WASSER",
	"PbNahmeDatum": "14.01.2013",
	"Parameter": "Atrazin",
	"Einheiten": "µg/L",
	"Wert Text": 0.006,
	"CAS": "1912-24-9",
	"Gruppe": "Pestizide",
	"DauerPN_h": 24,
	"Q_m3_s": 1060.71,
	"M_in_mg_L": 6,
	"Tage": 1,
	"Datum_Start": "13.01.2013",
	"mg_pro_24h": 6
},
{
	"PbTyp": "WASSER",
	"PbNahmeDatum": "15.01.2013",
	"Parameter": "Atrazin",
	"Einheiten": "µg/L",
	"Wert Text": 0.013,
	"CAS": "1912-24-9",
	"Gruppe": "Pestizide",
	"DauerPN_h": 24,
	"Q_m3_s": 1033.93,
	"M_in_mg_L": 13,
	"Tage": 1,
	"Datum_Start": "14.01.2013",
	"mg_pro_24h": 13
},
{
	"PbTyp": "WASSER",
	"PbNahmeDatum": "15.01.2013",
	"Parameter": "Atrazin",
	"Einheiten": "µg/L",
	"Wert Text": 0.005,
	"CAS": "1912-24-9",
	"Gruppe": "Pestizide",
	"DauerPN_h": 24,
	"Q_m3_s": 1033.93,
	"M_in_mg_L": 5,
	"Tage": 1,
	"Datum_Start": "14.01.2013",
	"mg_pro_24h": 5
},
{
	"PbTyp": "WASSER",
	"PbNahmeDatum": "16.01.2013",
	"Parameter": "Atrazin",
	"Einheiten": "µg/L",
	"Wert Text": 0.013,
	"CAS": "1912-24-9",
	"Gruppe": "Pestizide",
	"DauerPN_h": 24,
	"Q_m3_s": 1030.9,
	"M_in_mg_L": 13,
	"Tage": 1,
	"Datum_Start": "15.01.2013",
	"mg_pro_24h": 13
},
{
	"PbTyp": "WASSER",
	"PbNahmeDatum": "16.01.2013",
	"Parameter": "Atrazin",
	"Einheiten": "µg/L",
	"Wert Text": 0.005,
	"CAS": "1912-24-9",
	"Gruppe": "Pestizide",
	"DauerPN_h": 24,
	"Q_m3_s": 1030.9,
	"M_in_mg_L": 5,
	"Tage": 1,
	"Datum_Start": "15.01.2013",
	"mg_pro_24h": 5
},
{
	"PbTyp": "WASSER",
	"PbNahmeDatum": "17.01.2013",
	"Parameter": "Atrazin",
	"Einheiten": "µg/L",
	"Wert Text": 0.013,
	"CAS": "1912-24-9",
	"Gruppe": "Pestizide",
	"DauerPN_h": 24,
	"Q_m3_s": 979.29,
	"M_in_mg_L": 13,
	"Tage": 1,
	"Datum_Start": "16.01.2013",
	"mg_pro_24h": 13
},
{
	"PbTyp": "WASSER",
	"PbNahmeDatum": "17.01.2013",
	"Parameter": "Atrazin",
	"Einheiten": "µg/L",
	"Wert Text": 0.006,
	"CAS": "1912-24-9",
	"Gruppe": "Pestizide",
	"DauerPN_h": 24,
	"Q_m3_s": 979.29,
	"M_in_mg_L": 6,
	"Tage": 1,
	"Datum_Start": "16.01.2013",
	"mg_pro_24h": 6
},
{
	"PbTyp": "WASSER",
	"PbNahmeDatum": "18.01.2013",
	"Parameter": "Atrazin",
	"Einheiten": "µg/L",
	"Wert Text": 0.013,
	"CAS": "1912-24-9",
	"Gruppe": "Pestizide",
	"DauerPN_h": 24,
	"Q_m3_s": 966.53,
	"M_in_mg_L": 13,
	"Tage": 1,
	"Datum_Start": "17.01.2013",
	"mg_pro_24h": 13
},
{
	"PbTyp": "WASSER",
	"PbNahmeDatum": "19.01.2013",
	"Parameter": "Atrazin",
	"Einheiten": "µg/L",
	"Wert Text": 0.013,
	"CAS": "1912-24-9",
	"Gruppe": "Pestizide",
	"DauerPN_h": 24,
	"Q_m3_s": 928.28,
	"M_in_mg_L": 13,
	"Tage": 1,
	"Datum_Start": "18.01.2013",
	"mg_pro_24h": 13
},
{
	"PbTyp": "WASSER",
	"PbNahmeDatum": "20.01.2013",
	"Parameter": "Atrazin",
	"Einheiten": "µg/L",
	"Wert Text": 0.012,
	"CAS": "1912-24-9",
	"Gruppe": "Pestizide",
	"DauerPN_h": 24,
	"Q_m3_s": 896.46,
	"M_in_mg_L": 12,
	"Tage": 1,
	"Datum_Start": "19.01.2013",
	"mg_pro_24h": 12
},
{
	"PbTyp": "WASSER",
	"PbNahmeDatum": "20.01.2013",
	"Parameter": "Atrazin",
	"Einheiten": "µg/L",
	"Wert Text": 0.005,
	"CAS": "1912-24-9",
	"Gruppe": "Pestizide",
	"DauerPN_h": 24,
	"Q_m3_s": 896.46,
	"M_in_mg_L": 5,
	"Tage": 1,
	"Datum_Start": "19.01.2013",
	"mg_pro_24h": 5
},
{
	"PbTyp": "WASSER",
	"PbNahmeDatum": "21.01.2013",
	"Parameter": "Atrazin",
	"Einheiten": "µg/L",
	"Wert Text": 0.012,
	"CAS": "1912-24-9",
	"Gruppe": "Pestizide",
	"DauerPN_h": 24,
	"Q_m3_s": 855.04,
	"M_in_mg_L": 12,
	"Tage": 1,
	"Datum_Start": "20.01.2013",
	"mg_pro_24h": 12
},
{
	"PbTyp": "WASSER",
	"PbNahmeDatum": "22.01.2013",
	"Parameter": "Atrazin",
	"Einheiten": "µg/L",
	"Wert Text": 0.013,
	"CAS": "1912-24-9",
	"Gruppe": "Pestizide",
	"DauerPN_h": 24,
	"Q_m3_s": 846.98,
	"M_in_mg_L": 13,
	"Tage": 1,
	"Datum_Start": "21.01.2013",
	"mg_pro_24h": 13
},
{
	"PbTyp": "WASSER",
	"PbNahmeDatum": "22.01.2013",
	"Parameter": "Atrazin",
	"Einheiten": "µg/L",
	"Wert Text": 0.006,
	"CAS": "1912-24-9",
	"Gruppe": "Pestizide",
	"DauerPN_h": 24,
	"Q_m3_s": 846.98,
	"M_in_mg_L": 6,
	"Tage": 1,
	"Datum_Start": "21.01.2013",
	"mg_pro_24h": 6
},
{
	"PbTyp": "WASSER",
	"PbNahmeDatum": "23.01.2013",
	"Parameter": "Atrazin",
	"Einheiten": "µg/L",
	"Wert Text": 0.014,
	"CAS": "1912-24-9",
	"Gruppe": "Pestizide",
	"DauerPN_h": 24,
	"Q_m3_s": 837.4,
	"M_in_mg_L": 14,
	"Tage": 1,
	"Datum_Start": "22.01.2013",
	"mg_pro_24h": 14
},
{
	"PbTyp": "WASSER",
	"PbNahmeDatum": "23.01.2013",
	"Parameter": "Atrazin",
	"Einheiten": "µg/L",
	"Wert Text": 0.005,
	"CAS": "1912-24-9",
	"Gruppe": "Pestizide",
	"DauerPN_h": 24,
	"Q_m3_s": 837.4,
	"M_in_mg_L": 5,
	"Tage": 1,
	"Datum_Start": "22.01.2013",
	"mg_pro_24h": 5
},
{
	"PbTyp": "WASSER",
	"PbNahmeDatum": "24.01.2013",
	"Parameter": "Atrazin",
	"Einheiten": "µg/L",
	"Wert Text": 0.013,
	"CAS": "1912-24-9",
	"Gruppe": "Pestizide",
	"DauerPN_h": 24,
	"Q_m3_s": 825.72,
	"M_in_mg_L": 13,
	"Tage": 1,
	"Datum_Start": "23.01.2013",
	"mg_pro_24h": 13
},
{
	"PbTyp": "WASSER",
	"PbNahmeDatum": "25.01.2013",
	"Parameter": "Atrazin",
	"Einheiten": "µg/L",
	"Wert Text": 0.016,
	"CAS": "1912-24-9",
	"Gruppe": "Pestizide",
	"DauerPN_h": 24,
	"Q_m3_s": 847.04,
	"M_in_mg_L": 16,
	"Tage": 1,
	"Datum_Start": "24.01.2013",
	"mg_pro_24h": 16
},
{
	"PbTyp": "WASSER",
	"PbNahmeDatum": "25.01.2013",
	"Parameter": "Atrazin",
	"Einheiten": "µg/L",
	"Wert Text": 0.008,
	"CAS": "1912-24-9",
	"Gruppe": "Pestizide",
	"DauerPN_h": 24,
	"Q_m3_s": 847.04,
	"M_in_mg_L": 8,
	"Tage": 1,
	"Datum_Start": "24.01.2013",
	"mg_pro_24h": 8
},
{
	"PbTyp": "WASSER",
	"PbNahmeDatum": "26.01.2013",
	"Parameter": "Atrazin",
	"Einheiten": "µg/L",
	"Wert Text": 0.012,
	"CAS": "1912-24-9",
	"Gruppe": "Pestizide",
	"DauerPN_h": 24,
	"Q_m3_s": 791.7,
	"M_in_mg_L": 12,
	"Tage": 1,
	"Datum_Start": "25.01.2013",
	"mg_pro_24h": 12
},
{
	"PbTyp": "WASSER",
	"PbNahmeDatum": "27.01.2013",
	"Parameter": "Atrazin",
	"Einheiten": "µg/L",
	"Wert Text": 0.013,
	"CAS": "1912-24-9",
	"Gruppe": "Pestizide",
	"DauerPN_h": 24,
	"Q_m3_s": 742.12,
	"M_in_mg_L": 13,
	"Tage": 1,
	"Datum_Start": "26.01.2013",
	"mg_pro_24h": 13
},
{
	"PbTyp": "WASSER",
	"PbNahmeDatum": "27.01.2013",
	"Parameter": "Atrazin",
	"Einheiten": "µg/L",
	"Wert Text": 0.005,
	"CAS": "1912-24-9",
	"Gruppe": "Pestizide",
	"DauerPN_h": 24,
	"Q_m3_s": 742.12,
	"M_in_mg_L": 5,
	"Tage": 1,
	"Datum_Start": "26.01.2013",
	"mg_pro_24h": 5
},
{
	"PbTyp": "WASSER",
	"PbNahmeDatum": "28.01.2013",
	"Parameter": "Atrazin",
	"Einheiten": "µg/L",
	"Wert Text": 0.012,
	"CAS": "1912-24-9",
	"Gruppe": "Pestizide",
	"DauerPN_h": 24,
	"Q_m3_s": 734.06,
	"M_in_mg_L": 12,
	"Tage": 1,
	"Datum_Start": "27.01.2013",
	"mg_pro_24h": 12
},
{
	"PbTyp": "WASSER",
	"PbNahmeDatum": "29.01.2013",
	"Parameter": "Atrazin",
	"Einheiten": "µg/L",
	"Wert Text": 0.013,
	"CAS": "1912-24-9",
	"Gruppe": "Pestizide",
	"DauerPN_h": 24,
	"Q_m3_s": 791.29,
	"M_in_mg_L": 13,
	"Tage": 1,
	"Datum_Start": "28.01.2013",
	"mg_pro_24h": 13
},
{
	"PbTyp": "WASSER",
	"PbNahmeDatum": "29.01.2013",
	"Parameter": "Atrazin",
	"Einheiten": "µg/L",
	"Wert Text": 0.005,
	"CAS": "1912-24-9",
	"Gruppe": "Pestizide",
	"DauerPN_h": 24,
	"Q_m3_s": 791.29,
	"M_in_mg_L": 5,
	"Tage": 1,
	"Datum_Start": "28.01.2013",
	"mg_pro_24h": 5
},
{
	"PbTyp": "WASSER",
	"PbNahmeDatum": "30.01.2013",
	"Parameter": "Atrazin",
	"Einheiten": "µg/L",
	"Wert Text": 0.012,
	"CAS": "1912-24-9",
	"Gruppe": "Pestizide",
	"DauerPN_h": 24,
	"Q_m3_s": 903.94,
	"M_in_mg_L": 12,
	"Tage": 1,
	"Datum_Start": "29.01.2013",
	"mg_pro_24h": 12
},
{
	"PbTyp": "WASSER",
	"PbNahmeDatum": "31.01.2013",
	"Parameter": "Atrazin",
	"Einheiten": "µg/L",
	"Wert Text": 0.012,
	"CAS": "1912-24-9",
	"Gruppe": "Pestizide",
	"DauerPN_h": 24,
	"Q_m3_s": 1224.17,
	"M_in_mg_L": 12,
	"Tage": 1,
	"Datum_Start": "30.01.2013",
	"mg_pro_24h": 12
},
{
	"PbTyp": "WASSER",
	"PbNahmeDatum": "01.02.2013",
	"Parameter": "Atrazin",
	"Einheiten": "µg/L",
	"Wert Text": 0.012,
	"CAS": "1912-24-9",
	"Gruppe": "Pestizide",
	"DauerPN_h": 24,
	"Q_m3_s": 1446.6,
	"M_in_mg_L": 12,
	"Tage": 1,
	"Datum_Start": "31.01.2013",
	"mg_pro_24h": 12
},
{
	"PbTyp": "WASSER",
	"PbNahmeDatum": "02.02.2013",
	"Parameter": "Atrazin",
	"Einheiten": "µg/L",
	"Wert Text": 0.012,
	"CAS": "1912-24-9",
	"Gruppe": "Pestizide",
	"DauerPN_h": 24,
	"Q_m3_s": 1611.9,
	"M_in_mg_L": 12,
	"Tage": 1,
	"Datum_Start": "01.02.2013",
	"mg_pro_24h": 12
},
{
	"PbTyp": "WASSER",
	"PbNahmeDatum": "03.02.2013",
	"Parameter": "Atrazin",
	"Einheiten": "µg/L",
	"Wert Text": 0.011,
	"CAS": "1912-24-9",
	"Gruppe": "Pestizide",
	"DauerPN_h": 24,
	"Q_m3_s": 2371.66,
	"M_in_mg_L": 11,
	"Tage": 1,
	"Datum_Start": "02.02.2013",
	"mg_pro_24h": 11
},
{
	"PbTyp": "WASSER",
	"PbNahmeDatum": "04.02.2013",
	"Parameter": "Atrazin",
	"Einheiten": "µg/L",
	"Wert Text": 0.011,
	"CAS": "1912-24-9",
	"Gruppe": "Pestizide",
	"DauerPN_h": 24,
	"Q_m3_s": 1814.01,
	"M_in_mg_L": 11,
	"Tage": 1,
	"Datum_Start": "03.02.2013",
	"mg_pro_24h": 11
},
{
	"PbTyp": "WASSER",
	"PbNahmeDatum": "05.02.2013",
	"Parameter": "Atrazin",
	"Einheiten": "µg/L",
	"Wert Text": 0.012,
	"CAS": "1912-24-9",
	"Gruppe": "Pestizide",
	"DauerPN_h": 24,
	"Q_m3_s": 1748.95,
	"M_in_mg_L": 12,
	"Tage": 1,
	"Datum_Start": "04.02.2013",
	"mg_pro_24h": 12
},
{
	"PbTyp": "WASSER",
	"PbNahmeDatum": "06.02.2013",
	"Parameter": "Atrazin",
	"Einheiten": "µg/L",
	"Wert Text": 0.013,
	"CAS": "1912-24-9",
	"Gruppe": "Pestizide",
	"DauerPN_h": 24,
	"Q_m3_s": 1880.63,
	"M_in_mg_L": 13,
	"Tage": 1,
	"Datum_Start": "05.02.2013",
	"mg_pro_24h": 13
},
{
	"PbTyp": "WASSER",
	"PbNahmeDatum": "07.02.2013",
	"Parameter": "Atrazin",
	"Einheiten": "µg/L",
	"Wert Text": 0.012,
	"CAS": "1912-24-9",
	"Gruppe": "Pestizide",
	"DauerPN_h": 24,
	"Q_m3_s": 1726.22,
	"M_in_mg_L": 12,
	"Tage": 1,
	"Datum_Start": "06.02.2013",
	"mg_pro_24h": 12
},
{
	"PbTyp": "WASSER",
	"PbNahmeDatum": "08.02.2013",
	"Parameter": "Atrazin",
	"Einheiten": "µg/L",
	"Wert Text": 0.011,
	"CAS": "1912-24-9",
	"Gruppe": "Pestizide",
	"DauerPN_h": 24,
	"Q_m3_s": 1570.38,
	"M_in_mg_L": 11,
	"Tage": 1,
	"Datum_Start": "07.02.2013",
	"mg_pro_24h": 11
},
{
	"PbTyp": "WASSER",
	"PbNahmeDatum": "09.02.2013",
	"Parameter": "Atrazin",
	"Einheiten": "µg/L",
	"Wert Text": 0.007,
	"CAS": "1912-24-9",
	"Gruppe": "Pestizide",
	"DauerPN_h": 24,
	"Q_m3_s": 1506.95,
	"M_in_mg_L": 7,
	"Tage": 1,
	"Datum_Start": "08.02.2013",
	"mg_pro_24h": 7
},
{
	"PbTyp": "WASSER",
	"PbNahmeDatum": "10.02.2013",
	"Parameter": "Atrazin",
	"Einheiten": "µg/L",
	"Wert Text": 0.006,
	"CAS": "1912-24-9",
	"Gruppe": "Pestizide",
	"DauerPN_h": 24,
	"Q_m3_s": 1365.16,
	"M_in_mg_L": 6,
	"Tage": 1,
	"Datum_Start": "09.02.2013",
	"mg_pro_24h": 6
},
{
	"PbTyp": "WASSER",
	"PbNahmeDatum": "11.02.2013",
	"Parameter": "Atrazin",
	"Einheiten": "µg/L",
	"Wert Text": 0.006,
	"CAS": "1912-24-9",
	"Gruppe": "Pestizide",
	"DauerPN_h": 24,
	"Q_m3_s": 1255.79,
	"M_in_mg_L": 6,
	"Tage": 1,
	"Datum_Start": "10.02.2013",
	"mg_pro_24h": 6
},
{
	"PbTyp": "WASSER",
	"PbNahmeDatum": "12.02.2013",
	"Parameter": "Atrazin",
	"Einheiten": "µg/L",
	"Wert Text": 0.006,
	"CAS": "1912-24-9",
	"Gruppe": "Pestizide",
	"DauerPN_h": 24,
	"Q_m3_s": 1201.21,
	"M_in_mg_L": 6,
	"Tage": 1,
	"Datum_Start": "11.02.2013",
	"mg_pro_24h": 6
},
{
	"PbTyp": "WASSER",
	"PbNahmeDatum": "13.02.2013",
	"Parameter": "Atrazin",
	"Einheiten": "µg/L",
	"Wert Text": 0.007,
	"CAS": "1912-24-9",
	"Gruppe": "Pestizide",
	"DauerPN_h": 24,
	"Q_m3_s": 1238.82,
	"M_in_mg_L": 7,
	"Tage": 1,
	"Datum_Start": "12.02.2013",
	"mg_pro_24h": 7
},
{
	"PbTyp": "WASSER",
	"PbNahmeDatum": "13.02.2013",
	"Parameter": "Atrazin",
	"Einheiten": "µg/L",
	"Wert Text": 0.006,
	"CAS": "1912-24-9",
	"Gruppe": "Pestizide",
	"DauerPN_h": 24,
	"Q_m3_s": 1238.82,
	"M_in_mg_L": 6,
	"Tage": 1,
	"Datum_Start": "12.02.2013",
	"mg_pro_24h": 6
},
{
	"PbTyp": "WASSER",
	"PbNahmeDatum": "14.02.2013",
	"Parameter": "Atrazin",
	"Einheiten": "µg/L",
	"Wert Text": 0.007,
	"CAS": "1912-24-9",
	"Gruppe": "Pestizide",
	"DauerPN_h": 24,
	"Q_m3_s": 1188.28,
	"M_in_mg_L": 7,
	"Tage": 1,
	"Datum_Start": "13.02.2013",
	"mg_pro_24h": 7
},
{
	"PbTyp": "WASSER",
	"PbNahmeDatum": "15.02.2013",
	"Parameter": "Atrazin",
	"Einheiten": "µg/L",
	"Wert Text": 0.006,
	"CAS": "1912-24-9",
	"Gruppe": "Pestizide",
	"DauerPN_h": 24,
	"Q_m3_s": 1112.05,
	"M_in_mg_L": 6,
	"Tage": 1,
	"Datum_Start": "14.02.2013",
	"mg_pro_24h": 6
},
{
	"PbTyp": "WASSER",
	"PbNahmeDatum": "16.02.2013",
	"Parameter": "Atrazin",
	"Einheiten": "µg/L",
	"Wert Text": 0.006,
	"CAS": "1912-24-9",
	"Gruppe": "Pestizide",
	"DauerPN_h": 24,
	"Q_m3_s": 1105.87,
	"M_in_mg_L": 6,
	"Tage": 1,
	"Datum_Start": "15.02.2013",
	"mg_pro_24h": 6
},
{
	"PbTyp": "WASSER",
	"PbNahmeDatum": "16.02.2013",
	"Parameter": "Atrazin",
	"Einheiten": "µg/L",
	"Wert Text": 0.006,
	"CAS": "1912-24-9",
	"Gruppe": "Pestizide",
	"DauerPN_h": 24,
	"Q_m3_s": 1105.87,
	"M_in_mg_L": 6,
	"Tage": 1,
	"Datum_Start": "15.02.2013",
	"mg_pro_24h": 6
},
{
	"PbTyp": "WASSER",
	"PbNahmeDatum": "17.02.2013",
	"Parameter": "Atrazin",
	"Einheiten": "µg/L",
	"Wert Text": 0.006,
	"CAS": "1912-24-9",
	"Gruppe": "Pestizide",
	"DauerPN_h": 24,
	"Q_m3_s": 1009.66,
	"M_in_mg_L": 6,
	"Tage": 1,
	"Datum_Start": "16.02.2013",
	"mg_pro_24h": 6
},
{
	"PbTyp": "WASSER",
	"PbNahmeDatum": "18.02.2013",
	"Parameter": "Atrazin",
	"Einheiten": "µg/L",
	"Wert Text": 0.006,
	"CAS": "1912-24-9",
	"Gruppe": "Pestizide",
	"DauerPN_h": 24,
	"Q_m3_s": 971.95,
	"M_in_mg_L": 6,
	"Tage": 1,
	"Datum_Start": "17.02.2013",
	"mg_pro_24h": 6
},
{
	"PbTyp": "WASSER",
	"PbNahmeDatum": "19.02.2013",
	"Parameter": "Atrazin",
	"Einheiten": "µg/L",
	"Wert Text": 0.005,
	"CAS": "1912-24-9",
	"Gruppe": "Pestizide",
	"DauerPN_h": 24,
	"Q_m3_s": 967.65,
	"M_in_mg_L": 5,
	"Tage": 1,
	"Datum_Start": "18.02.2013",
	"mg_pro_24h": 5
},
{
	"PbTyp": "WASSER",
	"PbNahmeDatum": "20.02.2013",
	"Parameter": "Atrazin",
	"Einheiten": "µg/L",
	"Wert Text": 0.005,
	"CAS": "1912-24-9",
	"Gruppe": "Pestizide",
	"DauerPN_h": 24,
	"Q_m3_s": 947.28,
	"M_in_mg_L": 5,
	"Tage": 1,
	"Datum_Start": "19.02.2013",
	"mg_pro_24h": 5
},
{
	"PbTyp": "WASSER",
	"PbNahmeDatum": "22.02.2013",
	"Parameter": "Atrazin",
	"Einheiten": "µg/L",
	"Wert Text": 0.006,
	"CAS": "1912-24-9",
	"Gruppe": "Pestizide",
	"DauerPN_h": 24,
	"Q_m3_s": 902.35,
	"M_in_mg_L": 6,
	"Tage": 1,
	"Datum_Start": "21.02.2013",
	"mg_pro_24h": 6
},
{
	"PbTyp": "WASSER",
	"PbNahmeDatum": "24.02.2013",
	"Parameter": "Atrazin",
	"Einheiten": "µg/L",
	"Wert Text": 0.005,
	"CAS": "1912-24-9",
	"Gruppe": "Pestizide",
	"DauerPN_h": 24,
	"Q_m3_s": 822.01,
	"M_in_mg_L": 5,
	"Tage": 1,
	"Datum_Start": "23.02.2013",
	"mg_pro_24h": 5
},
{
	"PbTyp": "WASSER",
	"PbNahmeDatum": "25.02.2013",
	"Parameter": "Atrazin",
	"Einheiten": "µg/L",
	"Wert Text": 0.006,
	"CAS": "1912-24-9",
	"Gruppe": "Pestizide",
	"DauerPN_h": 24,
	"Q_m3_s": 808.96,
	"M_in_mg_L": 6,
	"Tage": 1,
	"Datum_Start": "24.02.2013",
	"mg_pro_24h": 6
},
{
	"PbTyp": "WASSER",
	"PbNahmeDatum": "25.02.2013",
	"Parameter": "Atrazin",
	"Einheiten": "µg/L",
	"Wert Text": 0.006,
	"CAS": "1912-24-9",
	"Gruppe": "Pestizide",
	"DauerPN_h": 24,
	"Q_m3_s": 808.96,
	"M_in_mg_L": 6,
	"Tage": 1,
	"Datum_Start": "24.02.2013",
	"mg_pro_24h": 6
},
{
	"PbTyp": "WASSER",
	"PbNahmeDatum": "26.02.2013",
	"Parameter": "Atrazin",
	"Einheiten": "µg/L",
	"Wert Text": 0.006,
	"CAS": "1912-24-9",
	"Gruppe": "Pestizide",
	"DauerPN_h": 24,
	"Q_m3_s": 820.6,
	"M_in_mg_L": 6,
	"Tage": 1,
	"Datum_Start": "25.02.2013",
	"mg_pro_24h": 6
},
{
	"PbTyp": "WASSER",
	"PbNahmeDatum": "27.02.2013",
	"Parameter": "Atrazin",
	"Einheiten": "µg/L",
	"Wert Text": 0.007,
	"CAS": "1912-24-9",
	"Gruppe": "Pestizide",
	"DauerPN_h": 24,
	"Q_m3_s": 791.67,
	"M_in_mg_L": 7,
	"Tage": 1,
	"Datum_Start": "26.02.2013",
	"mg_pro_24h": 7
},
{
	"PbTyp": "WASSER",
	"PbNahmeDatum": "27.02.2013",
	"Parameter": "Atrazin",
	"Einheiten": "µg/L",
	"Wert Text": 0.005,
	"CAS": "1912-24-9",
	"Gruppe": "Pestizide",
	"DauerPN_h": 24,
	"Q_m3_s": 791.67,
	"M_in_mg_L": 5,
	"Tage": 1,
	"Datum_Start": "26.02.2013",
	"mg_pro_24h": 5
},
{
	"PbTyp": "WASSER",
	"PbNahmeDatum": "28.02.2013",
	"Parameter": "Atrazin",
	"Einheiten": "µg/L",
	"Wert Text": 0.006,
	"CAS": "1912-24-9",
	"Gruppe": "Pestizide",
	"DauerPN_h": 24,
	"Q_m3_s": 812.94,
	"M_in_mg_L": 6,
	"Tage": 1,
	"Datum_Start": "27.02.2013",
	"mg_pro_24h": 6
},
{
	"PbTyp": "WASSER",
	"PbNahmeDatum": "28.02.2013",
	"Parameter": "Atrazin",
	"Einheiten": "µg/L",
	"Wert Text": 0.005,
	"CAS": "1912-24-9",
	"Gruppe": "Pestizide",
	"DauerPN_h": 24,
	"Q_m3_s": 812.94,
	"M_in_mg_L": 5,
	"Tage": 1,
	"Datum_Start": "27.02.2013",
	"mg_pro_24h": 5
},
{
	"PbTyp": "WASSER",
	"PbNahmeDatum": "01.03.2013",
	"Parameter": "Atrazin",
	"Einheiten": "µg/L",
	"Wert Text": 0.006,
	"CAS": "1912-24-9",
	"Gruppe": "Pestizide",
	"DauerPN_h": 24,
	"Q_m3_s": 794.49,
	"M_in_mg_L": 6,
	"Tage": 1,
	"Datum_Start": "28.02.2013",
	"mg_pro_24h": 6
},
{
	"PbTyp": "WASSER",
	"PbNahmeDatum": "05.03.2013",
	"Parameter": "Atrazin",
	"Einheiten": "µg/L",
	"Wert Text": 0.005,
	"CAS": "1912-24-9",
	"Gruppe": "Pestizide",
	"DauerPN_h": 24,
	"Q_m3_s": 716.61,
	"M_in_mg_L": 5,
	"Tage": 1,
	"Datum_Start": "04.03.2013",
	"mg_pro_24h": 5
},
{
	"PbTyp": "WASSER",
	"PbNahmeDatum": "06.03.2013",
	"Parameter": "Atrazin",
	"Einheiten": "µg/L",
	"Wert Text": 0.006,
	"CAS": "1912-24-9",
	"Gruppe": "Pestizide",
	"DauerPN_h": 24,
	"Q_m3_s": 720.1,
	"M_in_mg_L": 6,
	"Tage": 1,
	"Datum_Start": "05.03.2013",
	"mg_pro_24h": 6
},
{
	"PbTyp": "WASSER",
	"PbNahmeDatum": "07.03.2013",
	"Parameter": "Atrazin",
	"Einheiten": "µg/L",
	"Wert Text": 0.006,
	"CAS": "1912-24-9",
	"Gruppe": "Pestizide",
	"DauerPN_h": 24,
	"Q_m3_s": 752.9,
	"M_in_mg_L": 6,
	"Tage": 1,
	"Datum_Start": "06.03.2013",
	"mg_pro_24h": 6
},
{
	"PbTyp": "WASSER",
	"PbNahmeDatum": "08.03.2013",
	"Parameter": "Atrazin",
	"Einheiten": "µg/L",
	"Wert Text": 0.006,
	"CAS": "1912-24-9",
	"Gruppe": "Pestizide",
	"DauerPN_h": 24,
	"Q_m3_s": 831.61,
	"M_in_mg_L": 6,
	"Tage": 1,
	"Datum_Start": "07.03.2013",
	"mg_pro_24h": 6
},
{
	"PbTyp": "WASSER",
	"PbNahmeDatum": "13.03.2013",
	"Parameter": "Atrazin",
	"Einheiten": "µg/L",
	"Wert Text": 0.006,
	"CAS": "1912-24-9",
	"Gruppe": "Pestizide",
	"DauerPN_h": 24,
	"Q_m3_s": 1042.43,
	"M_in_mg_L": 6,
	"Tage": 1,
	"Datum_Start": "12.03.2013",
	"mg_pro_24h": 6
},
{
	"PbTyp": "WASSER",
	"PbNahmeDatum": "14.03.2013",
	"Parameter": "Atrazin",
	"Einheiten": "µg/L",
	"Wert Text": 0.005,
	"CAS": "1912-24-9",
	"Gruppe": "Pestizide",
	"DauerPN_h": 24,
	"Q_m3_s": 999.64,
	"M_in_mg_L": 5,
	"Tage": 1,
	"Datum_Start": "13.03.2013",
	"mg_pro_24h": 5
},
{
	"PbTyp": "WASSER",
	"PbNahmeDatum": "15.03.2013",
	"Parameter": "Atrazin",
	"Einheiten": "µg/L",
	"Wert Text": 0.006,
	"CAS": "1912-24-9",
	"Gruppe": "Pestizide",
	"DauerPN_h": 24,
	"Q_m3_s": 924.26,
	"M_in_mg_L": 6,
	"Tage": 1,
	"Datum_Start": "14.03.2013",
	"mg_pro_24h": 6
},
{
	"PbTyp": "WASSER",
	"PbNahmeDatum": "16.03.2013",
	"Parameter": "Atrazin",
	"Einheiten": "µg/L",
	"Wert Text": 0.007,
	"CAS": "1912-24-9",
	"Gruppe": "Pestizide",
	"DauerPN_h": 24,
	"Q_m3_s": 913.69,
	"M_in_mg_L": 7,
	"Tage": 1,
	"Datum_Start": "15.03.2013",
	"mg_pro_24h": 7
},
{
	"PbTyp": "WASSER",
	"PbNahmeDatum": "16.03.2013",
	"Parameter": "Atrazin",
	"Einheiten": "µg/L",
	"Wert Text": 0.006,
	"CAS": "1912-24-9",
	"Gruppe": "Pestizide",
	"DauerPN_h": 24,
	"Q_m3_s": 913.69,
	"M_in_mg_L": 6,
	"Tage": 1,
	"Datum_Start": "15.03.2013",
	"mg_pro_24h": 6
},
{
	"PbTyp": "WASSER",
	"PbNahmeDatum": "17.03.2013",
	"Parameter": "Atrazin",
	"Einheiten": "µg/L",
	"Wert Text": 0.007,
	"CAS": "1912-24-9",
	"Gruppe": "Pestizide",
	"DauerPN_h": 24,
	"Q_m3_s": 851.1,
	"M_in_mg_L": 7,
	"Tage": 1,
	"Datum_Start": "16.03.2013",
	"mg_pro_24h": 7
},
{
	"PbTyp": "WASSER",
	"PbNahmeDatum": "17.03.2013",
	"Parameter": "Atrazin",
	"Einheiten": "µg/L",
	"Wert Text": 0.005,
	"CAS": "1912-24-9",
	"Gruppe": "Pestizide",
	"DauerPN_h": 24,
	"Q_m3_s": 851.1,
	"M_in_mg_L": 5,
	"Tage": 1,
	"Datum_Start": "16.03.2013",
	"mg_pro_24h": 5
},
{
	"PbTyp": "WASSER",
	"PbNahmeDatum": "18.03.2013",
	"Parameter": "Atrazin",
	"Einheiten": "µg/L",
	"Wert Text": 0.006,
	"CAS": "1912-24-9",
	"Gruppe": "Pestizide",
	"DauerPN_h": 24,
	"Q_m3_s": 795.83,
	"M_in_mg_L": 6,
	"Tage": 1,
	"Datum_Start": "17.03.2013",
	"mg_pro_24h": 6
},
{
	"PbTyp": "WASSER",
	"PbNahmeDatum": "18.03.2013",
	"Parameter": "Atrazin",
	"Einheiten": "µg/L",
	"Wert Text": 0.005,
	"CAS": "1912-24-9",
	"Gruppe": "Pestizide",
	"DauerPN_h": 24,
	"Q_m3_s": 795.83,
	"M_in_mg_L": 5,
	"Tage": 1,
	"Datum_Start": "17.03.2013",
	"mg_pro_24h": 5
},
{
	"PbTyp": "WASSER",
	"PbNahmeDatum": "19.03.2013",
	"Parameter": "Atrazin",
	"Einheiten": "µg/L",
	"Wert Text": 0.006,
	"CAS": "1912-24-9",
	"Gruppe": "Pestizide",
	"DauerPN_h": 24,
	"Q_m3_s": 829.27,
	"M_in_mg_L": 6,
	"Tage": 1,
	"Datum_Start": "18.03.2013",
	"mg_pro_24h": 6
},
{
	"PbTyp": "WASSER",
	"PbNahmeDatum": "20.03.2013",
	"Parameter": "Atrazin",
	"Einheiten": "µg/L",
	"Wert Text": 0.007,
	"CAS": "1912-24-9",
	"Gruppe": "Pestizide",
	"DauerPN_h": 24,
	"Q_m3_s": 845.09,
	"M_in_mg_L": 7,
	"Tage": 1,
	"Datum_Start": "19.03.2013",
	"mg_pro_24h": 7
},
{
	"PbTyp": "WASSER",
	"PbNahmeDatum": "21.03.2013",
	"Parameter": "Atrazin",
	"Einheiten": "µg/L",
	"Wert Text": 0.006,
	"CAS": "1912-24-9",
	"Gruppe": "Pestizide",
	"DauerPN_h": 24,
	"Q_m3_s": 861.44,
	"M_in_mg_L": 6,
	"Tage": 1,
	"Datum_Start": "20.03.2013",
	"mg_pro_24h": 6
},
{
	"PbTyp": "WASSER",
	"PbNahmeDatum": "22.03.2013",
	"Parameter": "Atrazin",
	"Einheiten": "µg/L",
	"Wert Text": 0.006,
	"CAS": "1912-24-9",
	"Gruppe": "Pestizide",
	"DauerPN_h": 24,
	"Q_m3_s": 820.09,
	"M_in_mg_L": 6,
	"Tage": 1,
	"Datum_Start": "21.03.2013",
	"mg_pro_24h": 6
},
{
	"PbTyp": "WASSER",
	"PbNahmeDatum": "22.03.2013",
	"Parameter": "Atrazin",
	"Einheiten": "µg/L",
	"Wert Text": 0.005,
	"CAS": "1912-24-9",
	"Gruppe": "Pestizide",
	"DauerPN_h": 24,
	"Q_m3_s": 820.09,
	"M_in_mg_L": 5,
	"Tage": 1,
	"Datum_Start": "21.03.2013",
	"mg_pro_24h": 5
},
{
	"PbTyp": "WASSER",
	"PbNahmeDatum": "23.03.2013",
	"Parameter": "Atrazin",
	"Einheiten": "µg/L",
	"Wert Text": 0.006,
	"CAS": "1912-24-9",
	"Gruppe": "Pestizide",
	"DauerPN_h": 24,
	"Q_m3_s": 774.13,
	"M_in_mg_L": 6,
	"Tage": 1,
	"Datum_Start": "22.03.2013",
	"mg_pro_24h": 6
},
{
	"PbTyp": "WASSER",
	"PbNahmeDatum": "24.03.2013",
	"Parameter": "Atrazin",
	"Einheiten": "µg/L",
	"Wert Text": 0.006,
	"CAS": "1912-24-9",
	"Gruppe": "Pestizide",
	"DauerPN_h": 24,
	"Q_m3_s": 747.38,
	"M_in_mg_L": 6,
	"Tage": 1,
	"Datum_Start": "23.03.2013",
	"mg_pro_24h": 6
},
{
	"PbTyp": "WASSER",
	"PbNahmeDatum": "24.03.2013",
	"Parameter": "Atrazin",
	"Einheiten": "µg/L",
	"Wert Text": 0.005,
	"CAS": "1912-24-9",
	"Gruppe": "Pestizide",
	"DauerPN_h": 24,
	"Q_m3_s": 747.38,
	"M_in_mg_L": 5,
	"Tage": 1,
	"Datum_Start": "23.03.2013",
	"mg_pro_24h": 5
},
{
	"PbTyp": "WASSER",
	"PbNahmeDatum": "25.03.2013",
	"Parameter": "Atrazin",
	"Einheiten": "µg/L",
	"Wert Text": 0.006,
	"CAS": "1912-24-9",
	"Gruppe": "Pestizide",
	"DauerPN_h": 24,
	"Q_m3_s": 727.88,
	"M_in_mg_L": 6,
	"Tage": 1,
	"Datum_Start": "24.03.2013",
	"mg_pro_24h": 6
},
{
	"PbTyp": "WASSER",
	"PbNahmeDatum": "26.03.2013",
	"Parameter": "Atrazin",
	"Einheiten": "µg/L",
	"Wert Text": 0.006,
	"CAS": "1912-24-9",
	"Gruppe": "Pestizide",
	"DauerPN_h": 24,
	"Q_m3_s": 717.38,
	"M_in_mg_L": 6,
	"Tage": 1,
	"Datum_Start": "25.03.2013",
	"mg_pro_24h": 6
},
{
	"PbTyp": "WASSER",
	"PbNahmeDatum": "27.03.2013",
	"Parameter": "Atrazin",
	"Einheiten": "µg/L",
	"Wert Text": 0.006,
	"CAS": "1912-24-9",
	"Gruppe": "Pestizide",
	"DauerPN_h": 24,
	"Q_m3_s": 722.77,
	"M_in_mg_L": 6,
	"Tage": 1,
	"Datum_Start": "26.03.2013",
	"mg_pro_24h": 6
},
{
	"PbTyp": "WASSER",
	"PbNahmeDatum": "29.03.2013",
	"Parameter": "Atrazin",
	"Einheiten": "µg/L",
	"Wert Text": 0.005,
	"CAS": "1912-24-9",
	"Gruppe": "Pestizide",
	"DauerPN_h": 24,
	"Q_m3_s": 781.71,
	"M_in_mg_L": 5,
	"Tage": 1,
	"Datum_Start": "28.03.2013",
	"mg_pro_24h": 5
},
{
	"PbTyp": "WASSER",
	"PbNahmeDatum": "30.03.2013",
	"Parameter": "Atrazin",
	"Einheiten": "µg/L",
	"Wert Text": 0.006,
	"CAS": "1912-24-9",
	"Gruppe": "Pestizide",
	"DauerPN_h": 24,
	"Q_m3_s": 882.28,
	"M_in_mg_L": 6,
	"Tage": 1,
	"Datum_Start": "29.03.2013",
	"mg_pro_24h": 6
},
{
	"PbTyp": "WASSER",
	"PbNahmeDatum": "31.03.2013",
	"Parameter": "Atrazin",
	"Einheiten": "µg/L",
	"Wert Text": 0.005,
	"CAS": "1912-24-9",
	"Gruppe": "Pestizide",
	"DauerPN_h": 24,
	"Q_m3_s": 1010.73,
	"M_in_mg_L": 5,
	"Tage": 1,
	"Datum_Start": "30.03.2013",
	"mg_pro_24h": 5
},
{
	"PbTyp": "WASSER",
	"PbNahmeDatum": "04.04.2013",
	"Parameter": "Atrazin",
	"Einheiten": "µg/L",
	"Wert Text": 0.006,
	"CAS": "1912-24-9",
	"Gruppe": "Pestizide",
	"DauerPN_h": 24,
	"Q_m3_s": 929.72,
	"M_in_mg_L": 6,
	"Tage": 1,
	"Datum_Start": "03.04.2013",
	"mg_pro_24h": 6
},
{
	"PbTyp": "WASSER",
	"PbNahmeDatum": "05.04.2013",
	"Parameter": "Atrazin",
	"Einheiten": "µg/L",
	"Wert Text": 0.006,
	"CAS": "1912-24-9",
	"Gruppe": "Pestizide",
	"DauerPN_h": 24,
	"Q_m3_s": 902,
	"M_in_mg_L": 6,
	"Tage": 1,
	"Datum_Start": "04.04.2013",
	"mg_pro_24h": 6
},
{
	"PbTyp": "WASSER",
	"PbNahmeDatum": "06.04.2013",
	"Parameter": "Atrazin",
	"Einheiten": "µg/L",
	"Wert Text": 0.006,
	"CAS": "1912-24-9",
	"Gruppe": "Pestizide",
	"DauerPN_h": 24,
	"Q_m3_s": 867.43,
	"M_in_mg_L": 6,
	"Tage": 1,
	"Datum_Start": "05.04.2013",
	"mg_pro_24h": 6
},
{
	"PbTyp": "WASSER",
	"PbNahmeDatum": "06.04.2013",
	"Parameter": "Atrazin",
	"Einheiten": "µg/L",
	"Wert Text": 0.005,
	"CAS": "1912-24-9",
	"Gruppe": "Pestizide",
	"DauerPN_h": 24,
	"Q_m3_s": 867.43,
	"M_in_mg_L": 5,
	"Tage": 1,
	"Datum_Start": "05.04.2013",
	"mg_pro_24h": 5
},
{
	"PbTyp": "WASSER",
	"PbNahmeDatum": "08.04.2013",
	"Parameter": "Atrazin",
	"Einheiten": "µg/L",
	"Wert Text": 0.006,
	"CAS": "1912-24-9",
	"Gruppe": "Pestizide",
	"DauerPN_h": 24,
	"Q_m3_s": 760.7,
	"M_in_mg_L": 6,
	"Tage": 1,
	"Datum_Start": "07.04.2013",
	"mg_pro_24h": 6
},
{
	"PbTyp": "WASSER",
	"PbNahmeDatum": "09.04.2013",
	"Parameter": "Atrazin",
	"Einheiten": "µg/L",
	"Wert Text": 0.006,
	"CAS": "1912-24-9",
	"Gruppe": "Pestizide",
	"DauerPN_h": 24,
	"Q_m3_s": 751.2,
	"M_in_mg_L": 6,
	"Tage": 1,
	"Datum_Start": "08.04.2013",
	"mg_pro_24h": 6
},
{
	"PbTyp": "WASSER",
	"PbNahmeDatum": "09.04.2013",
	"Parameter": "Atrazin",
	"Einheiten": "µg/L",
	"Wert Text": 0.005,
	"CAS": "1912-24-9",
	"Gruppe": "Pestizide",
	"DauerPN_h": 24,
	"Q_m3_s": 751.2,
	"M_in_mg_L": 5,
	"Tage": 1,
	"Datum_Start": "08.04.2013",
	"mg_pro_24h": 5
},
{
	"PbTyp": "WASSER",
	"PbNahmeDatum": "10.04.2013",
	"Parameter": "Atrazin",
	"Einheiten": "µg/L",
	"Wert Text": 0.006,
	"CAS": "1912-24-9",
	"Gruppe": "Pestizide",
	"DauerPN_h": 24,
	"Q_m3_s": 838.21,
	"M_in_mg_L": 6,
	"Tage": 1,
	"Datum_Start": "09.04.2013",
	"mg_pro_24h": 6
},
{
	"PbTyp": "WASSER",
	"PbNahmeDatum": "10.04.2013",
	"Parameter": "Atrazin",
	"Einheiten": "µg/L",
	"Wert Text": 0.005,
	"CAS": "1912-24-9",
	"Gruppe": "Pestizide",
	"DauerPN_h": 24,
	"Q_m3_s": 838.21,
	"M_in_mg_L": 5,
	"Tage": 1,
	"Datum_Start": "09.04.2013",
	"mg_pro_24h": 5
},
{
	"PbTyp": "WASSER",
	"PbNahmeDatum": "11.04.2013",
	"Parameter": "Atrazin",
	"Einheiten": "µg/L",
	"Wert Text": 0.006,
	"CAS": "1912-24-9",
	"Gruppe": "Pestizide",
	"DauerPN_h": 24,
	"Q_m3_s": 881.51,
	"M_in_mg_L": 6,
	"Tage": 1,
	"Datum_Start": "10.04.2013",
	"mg_pro_24h": 6
},
{
	"PbTyp": "WASSER",
	"PbNahmeDatum": "12.04.2013",
	"Parameter": "Atrazin",
	"Einheiten": "µg/L",
	"Wert Text": 0.006,
	"CAS": "1912-24-9",
	"Gruppe": "Pestizide",
	"DauerPN_h": 24,
	"Q_m3_s": 1126.75,
	"M_in_mg_L": 6,
	"Tage": 1,
	"Datum_Start": "11.04.2013",
	"mg_pro_24h": 6
},
{
	"PbTyp": "WASSER",
	"PbNahmeDatum": "12.04.2013",
	"Parameter": "Atrazin",
	"Einheiten": "µg/L",
	"Wert Text": 0.005,
	"CAS": "1912-24-9",
	"Gruppe": "Pestizide",
	"DauerPN_h": 24,
	"Q_m3_s": 1126.75,
	"M_in_mg_L": 5,
	"Tage": 1,
	"Datum_Start": "11.04.2013",
	"mg_pro_24h": 5
},
{
	"PbTyp": "WASSER",
	"PbNahmeDatum": "13.04.2013",
	"Parameter": "Atrazin",
	"Einheiten": "µg/L",
	"Wert Text": 0.006,
	"CAS": "1912-24-9",
	"Gruppe": "Pestizide",
	"DauerPN_h": 24,
	"Q_m3_s": 1603.59,
	"M_in_mg_L": 6,
	"Tage": 1,
	"Datum_Start": "12.04.2013",
	"mg_pro_24h": 6
},
{
	"PbTyp": "WASSER",
	"PbNahmeDatum": "16.04.2013",
	"Parameter": "Atrazin",
	"Einheiten": "µg/L",
	"Wert Text": 0.005,
	"CAS": "1912-24-9",
	"Gruppe": "Pestizide",
	"DauerPN_h": 24,
	"Q_m3_s": 1253.86,
	"M_in_mg_L": 5,
	"Tage": 1,
	"Datum_Start": "15.04.2013",
	"mg_pro_24h": 5
},
{
	"PbTyp": "WASSER",
	"PbNahmeDatum": "18.04.2013",
	"Parameter": "Atrazin",
	"Einheiten": "µg/L",
	"Wert Text": 0.006,
	"CAS": "1912-24-9",
	"Gruppe": "Pestizide",
	"DauerPN_h": 24,
	"Q_m3_s": 1295.77,
	"M_in_mg_L": 6,
	"Tage": 1,
	"Datum_Start": "17.04.2013",
	"mg_pro_24h": 6
},
{
	"PbTyp": "WASSER",
	"PbNahmeDatum": "19.04.2013",
	"Parameter": "Atrazin",
	"Einheiten": "µg/L",
	"Wert Text": 0.006,
	"CAS": "1912-24-9",
	"Gruppe": "Pestizide",
	"DauerPN_h": 24,
	"Q_m3_s": 1349.81,
	"M_in_mg_L": 6,
	"Tage": 1,
	"Datum_Start": "18.04.2013",
	"mg_pro_24h": 6
},
{
	"PbTyp": "WASSER",
	"PbNahmeDatum": "19.04.2013",
	"Parameter": "Atrazin",
	"Einheiten": "µg/L",
	"Wert Text": 0.005,
	"CAS": "1912-24-9",
	"Gruppe": "Pestizide",
	"DauerPN_h": 24,
	"Q_m3_s": 1349.81,
	"M_in_mg_L": 5,
	"Tage": 1,
	"Datum_Start": "18.04.2013",
	"mg_pro_24h": 5
},
{
	"PbTyp": "WASSER",
	"PbNahmeDatum": "20.04.2013",
	"Parameter": "Atrazin",
	"Einheiten": "µg/L",
	"Wert Text": 0.008,
	"CAS": "1912-24-9",
	"Gruppe": "Pestizide",
	"DauerPN_h": 24,
	"Q_m3_s": 1721.04,
	"M_in_mg_L": 8,
	"Tage": 1,
	"Datum_Start": "19.04.2013",
	"mg_pro_24h": 8
},
{
	"PbTyp": "WASSER",
	"PbNahmeDatum": "20.04.2013",
	"Parameter": "Atrazin",
	"Einheiten": "µg/L",
	"Wert Text": 0.007,
	"CAS": "1912-24-9",
	"Gruppe": "Pestizide",
	"DauerPN_h": 24,
	"Q_m3_s": 1721.04,
	"M_in_mg_L": 7,
	"Tage": 1,
	"Datum_Start": "19.04.2013",
	"mg_pro_24h": 7
},
{
	"PbTyp": "WASSER",
	"PbNahmeDatum": "21.04.2013",
	"Parameter": "Atrazin",
	"Einheiten": "µg/L",
	"Wert Text": 0.005,
	"CAS": "1912-24-9",
	"Gruppe": "Pestizide",
	"DauerPN_h": 24,
	"Q_m3_s": 2187.35,
	"M_in_mg_L": 5,
	"Tage": 1,
	"Datum_Start": "20.04.2013",
	"mg_pro_24h": 5
},
{
	"PbTyp": "WASSER",
	"PbNahmeDatum": "21.04.2013",
	"Parameter": "Atrazin",
	"Einheiten": "µg/L",
	"Wert Text": 0.005,
	"CAS": "1912-24-9",
	"Gruppe": "Pestizide",
	"DauerPN_h": 24,
	"Q_m3_s": 2187.35,
	"M_in_mg_L": 5,
	"Tage": 1,
	"Datum_Start": "20.04.2013",
	"mg_pro_24h": 5
},
{
	"PbTyp": "WASSER",
	"PbNahmeDatum": "22.04.2013",
	"Parameter": "Atrazin",
	"Einheiten": "µg/L",
	"Wert Text": 0.005,
	"CAS": "1912-24-9",
	"Gruppe": "Pestizide",
	"DauerPN_h": 24,
	"Q_m3_s": 1999.45,
	"M_in_mg_L": 5,
	"Tage": 1,
	"Datum_Start": "21.04.2013",
	"mg_pro_24h": 5
},
{
	"PbTyp": "WASSER",
	"PbNahmeDatum": "22.04.2013",
	"Parameter": "Atrazin",
	"Einheiten": "µg/L",
	"Wert Text": 0.005,
	"CAS": "1912-24-9",
	"Gruppe": "Pestizide",
	"DauerPN_h": 24,
	"Q_m3_s": 1999.45,
	"M_in_mg_L": 5,
	"Tage": 1,
	"Datum_Start": "21.04.2013",
	"mg_pro_24h": 5
},
{
	"PbTyp": "WASSER",
	"PbNahmeDatum": "24.04.2013",
	"Parameter": "Atrazin",
	"Einheiten": "µg/L",
	"Wert Text": 0.006,
	"CAS": "1912-24-9",
	"Gruppe": "Pestizide",
	"DauerPN_h": 24,
	"Q_m3_s": 1680.28,
	"M_in_mg_L": 6,
	"Tage": 1,
	"Datum_Start": "23.04.2013",
	"mg_pro_24h": 6
},
{
	"PbTyp": "WASSER",
	"PbNahmeDatum": "25.04.2013",
	"Parameter": "Atrazin",
	"Einheiten": "µg/L",
	"Wert Text": 0.005,
	"CAS": "1912-24-9",
	"Gruppe": "Pestizide",
	"DauerPN_h": 24,
	"Q_m3_s": 1590.84,
	"M_in_mg_L": 5,
	"Tage": 1,
	"Datum_Start": "24.04.2013",
	"mg_pro_24h": 5
},
{
	"PbTyp": "WASSER",
	"PbNahmeDatum": "26.04.2013",
	"Parameter": "Atrazin",
	"Einheiten": "µg/L",
	"Wert Text": 0.005,
	"CAS": "1912-24-9",
	"Gruppe": "Pestizide",
	"DauerPN_h": 24,
	"Q_m3_s": 1534.17,
	"M_in_mg_L": 5,
	"Tage": 1,
	"Datum_Start": "25.04.2013",
	"mg_pro_24h": 5
},
{
	"PbTyp": "WASSER",
	"PbNahmeDatum": "27.04.2013",
	"Parameter": "Atrazin",
	"Einheiten": "µg/L",
	"Wert Text": 0.006,
	"CAS": "1912-24-9",
	"Gruppe": "Pestizide",
	"DauerPN_h": 24,
	"Q_m3_s": 1575.28,
	"M_in_mg_L": 6,
	"Tage": 1,
	"Datum_Start": "26.04.2013",
	"mg_pro_24h": 6
},
{
	"PbTyp": "WASSER",
	"PbNahmeDatum": "27.04.2013",
	"Parameter": "Atrazin",
	"Einheiten": "µg/L",
	"Wert Text": 0.005,
	"CAS": "1912-24-9",
	"Gruppe": "Pestizide",
	"DauerPN_h": 24,
	"Q_m3_s": 1575.28,
	"M_in_mg_L": 5,
	"Tage": 1,
	"Datum_Start": "26.04.2013",
	"mg_pro_24h": 5
},
{
	"PbTyp": "WASSER",
	"PbNahmeDatum": "28.04.2013",
	"Parameter": "Atrazin",
	"Einheiten": "µg/L",
	"Wert Text": 0.005,
	"CAS": "1912-24-9",
	"Gruppe": "Pestizide",
	"DauerPN_h": 24,
	"Q_m3_s": 1597.33,
	"M_in_mg_L": 5,
	"Tage": 1,
	"Datum_Start": "27.04.2013",
	"mg_pro_24h": 5
},
{
	"PbTyp": "WASSER",
	"PbNahmeDatum": "29.04.2013",
	"Parameter": "Atrazin",
	"Einheiten": "µg/L",
	"Wert Text": 0.006,
	"CAS": "1912-24-9",
	"Gruppe": "Pestizide",
	"DauerPN_h": 24,
	"Q_m3_s": 1582.28,
	"M_in_mg_L": 6,
	"Tage": 1,
	"Datum_Start": "28.04.2013",
	"mg_pro_24h": 6
},
{
	"PbTyp": "WASSER",
	"PbNahmeDatum": "30.04.2013",
	"Parameter": "Atrazin",
	"Einheiten": "µg/L",
	"Wert Text": 0.006,
	"CAS": "1912-24-9",
	"Gruppe": "Pestizide",
	"DauerPN_h": 24,
	"Q_m3_s": 1549.71,
	"M_in_mg_L": 6,
	"Tage": 1,
	"Datum_Start": "29.04.2013",
	"mg_pro_24h": 6
},
{
	"PbTyp": "WASSER",
	"PbNahmeDatum": "30.04.2013",
	"Parameter": "Atrazin",
	"Einheiten": "µg/L",
	"Wert Text": 0.005,
	"CAS": "1912-24-9",
	"Gruppe": "Pestizide",
	"DauerPN_h": 24,
	"Q_m3_s": 1549.71,
	"M_in_mg_L": 5,
	"Tage": 1,
	"Datum_Start": "29.04.2013",
	"mg_pro_24h": 5
},
{
	"PbTyp": "WASSER",
	"PbNahmeDatum": "01.05.2013",
	"Parameter": "Atrazin",
	"Einheiten": "µg/L",
	"Wert Text": 0.005,
	"CAS": "1912-24-9",
	"Gruppe": "Pestizide",
	"DauerPN_h": 24,
	"Q_m3_s": 1538.42,
	"M_in_mg_L": 5,
	"Tage": 1,
	"Datum_Start": "30.04.2013",
	"mg_pro_24h": 5
},
{
	"PbTyp": "WASSER",
	"PbNahmeDatum": "01.05.2013",
	"Parameter": "Atrazin",
	"Einheiten": "µg/L",
	"Wert Text": 0.006,
	"CAS": "1912-24-9",
	"Gruppe": "Pestizide",
	"DauerPN_h": 24,
	"Q_m3_s": 1538.42,
	"M_in_mg_L": 6,
	"Tage": 1,
	"Datum_Start": "30.04.2013",
	"mg_pro_24h": 6
},
{
	"PbTyp": "WASSER",
	"PbNahmeDatum": "03.05.2013",
	"Parameter": "Atrazin",
	"Einheiten": "µg/L",
	"Wert Text": 0.006,
	"CAS": "1912-24-9",
	"Gruppe": "Pestizide",
	"DauerPN_h": 24,
	"Q_m3_s": 1628.05,
	"M_in_mg_L": 6,
	"Tage": 1,
	"Datum_Start": "02.05.2013",
	"mg_pro_24h": 6
},
{
	"PbTyp": "WASSER",
	"PbNahmeDatum": "07.05.2013",
	"Parameter": "Atrazin",
	"Einheiten": "µg/L",
	"Wert Text": 0.005,
	"CAS": "1912-24-9",
	"Gruppe": "Pestizide",
	"DauerPN_h": 24,
	"Q_m3_s": 1609.58,
	"M_in_mg_L": 5,
	"Tage": 1,
	"Datum_Start": "06.05.2013",
	"mg_pro_24h": 5
},
{
	"PbTyp": "WASSER",
	"PbNahmeDatum": "08.05.2013",
	"Parameter": "Atrazin",
	"Einheiten": "µg/L",
	"Wert Text": 0.006,
	"CAS": "1912-24-9",
	"Gruppe": "Pestizide",
	"DauerPN_h": 24,
	"Q_m3_s": 1629.35,
	"M_in_mg_L": 6,
	"Tage": 1,
	"Datum_Start": "07.05.2013",
	"mg_pro_24h": 6
},
{
	"PbTyp": "WASSER",
	"PbNahmeDatum": "12.05.2013",
	"Parameter": "Atrazin",
	"Einheiten": "µg/L",
	"Wert Text": 0.005,
	"CAS": "1912-24-9",
	"Gruppe": "Pestizide",
	"DauerPN_h": 24,
	"Q_m3_s": 1742.52,
	"M_in_mg_L": 5,
	"Tage": 1,
	"Datum_Start": "11.05.2013",
	"mg_pro_24h": 5
},
{
	"PbTyp": "WASSER",
	"PbNahmeDatum": "17.05.2013",
	"Parameter": "Atrazin",
	"Einheiten": "µg/L",
	"Wert Text": 0.005,
	"CAS": "1912-24-9",
	"Gruppe": "Pestizide",
	"DauerPN_h": 24,
	"Q_m3_s": 1448.71,
	"M_in_mg_L": 5,
	"Tage": 1,
	"Datum_Start": "16.05.2013",
	"mg_pro_24h": 5
},
{
	"PbTyp": "WASSER",
	"PbNahmeDatum": "19.05.2013",
	"Parameter": "Atrazin",
	"Einheiten": "µg/L",
	"Wert Text": 0.005,
	"CAS": "1912-24-9",
	"Gruppe": "Pestizide",
	"DauerPN_h": 24,
	"Q_m3_s": 1461.08,
	"M_in_mg_L": 5,
	"Tage": 1,
	"Datum_Start": "18.05.2013",
	"mg_pro_24h": 5
},
{
	"PbTyp": "WASSER",
	"PbNahmeDatum": "20.05.2013",
	"Parameter": "Atrazin",
	"Einheiten": "µg/L",
	"Wert Text": 0.006,
	"CAS": "1912-24-9",
	"Gruppe": "Pestizide",
	"DauerPN_h": 24,
	"Q_m3_s": 1412.58,
	"M_in_mg_L": 6,
	"Tage": 1,
	"Datum_Start": "19.05.2013",
	"mg_pro_24h": 6
},
{
	"PbTyp": "WASSER",
	"PbNahmeDatum": "20.05.2013",
	"Parameter": "Atrazin",
	"Einheiten": "µg/L",
	"Wert Text": 0.005,
	"CAS": "1912-24-9",
	"Gruppe": "Pestizide",
	"DauerPN_h": 24,
	"Q_m3_s": 1412.58,
	"M_in_mg_L": 5,
	"Tage": 1,
	"Datum_Start": "19.05.2013",
	"mg_pro_24h": 5
},
{
	"PbTyp": "WASSER",
	"PbNahmeDatum": "21.05.2013",
	"Parameter": "Atrazin",
	"Einheiten": "µg/L",
	"Wert Text": 0.005,
	"CAS": "1912-24-9",
	"Gruppe": "Pestizide",
	"DauerPN_h": 24,
	"Q_m3_s": 1410.26,
	"M_in_mg_L": 5,
	"Tage": 1,
	"Datum_Start": "20.05.2013",
	"mg_pro_24h": 5
},
{
	"PbTyp": "WASSER",
	"PbNahmeDatum": "21.05.2013",
	"Parameter": "Atrazin",
	"Einheiten": "µg/L",
	"Wert Text": 0.005,
	"CAS": "1912-24-9",
	"Gruppe": "Pestizide",
	"DauerPN_h": 24,
	"Q_m3_s": 1410.26,
	"M_in_mg_L": 5,
	"Tage": 1,
	"Datum_Start": "20.05.2013",
	"mg_pro_24h": 5
},
{
	"PbTyp": "WASSER",
	"PbNahmeDatum": "22.05.2013",
	"Parameter": "Atrazin",
	"Einheiten": "µg/L",
	"Wert Text": 0.006,
	"CAS": "1912-24-9",
	"Gruppe": "Pestizide",
	"DauerPN_h": 24,
	"Q_m3_s": 1471.58,
	"M_in_mg_L": 6,
	"Tage": 1,
	"Datum_Start": "21.05.2013",
	"mg_pro_24h": 6
},
{
	"PbTyp": "WASSER",
	"PbNahmeDatum": "24.05.2013",
	"Parameter": "Atrazin",
	"Einheiten": "µg/L",
	"Wert Text": 0.005,
	"CAS": "1912-24-9",
	"Gruppe": "Pestizide",
	"DauerPN_h": 24,
	"Q_m3_s": 1704.44,
	"M_in_mg_L": 5,
	"Tage": 1,
	"Datum_Start": "23.05.2013",
	"mg_pro_24h": 5
},
{
	"PbTyp": "WASSER",
	"PbNahmeDatum": "25.05.2013",
	"Parameter": "Atrazin",
	"Einheiten": "µg/L",
	"Wert Text": 0.005,
	"CAS": "1912-24-9",
	"Gruppe": "Pestizide",
	"DauerPN_h": 24,
	"Q_m3_s": 1578.22,
	"M_in_mg_L": 5,
	"Tage": 1,
	"Datum_Start": "24.05.2013",
	"mg_pro_24h": 5
},
{
	"PbTyp": "WASSER",
	"PbNahmeDatum": "25.05.2013",
	"Parameter": "Atrazin",
	"Einheiten": "µg/L",
	"Wert Text": 0.005,
	"CAS": "1912-24-9",
	"Gruppe": "Pestizide",
	"DauerPN_h": 24,
	"Q_m3_s": 1578.22,
	"M_in_mg_L": 5,
	"Tage": 1,
	"Datum_Start": "24.05.2013",
	"mg_pro_24h": 5
},
{
	"PbTyp": "WASSER",
	"PbNahmeDatum": "26.05.2013",
	"Parameter": "Atrazin",
	"Einheiten": "µg/L",
	"Wert Text": 0.007,
	"CAS": "1912-24-9",
	"Gruppe": "Pestizide",
	"DauerPN_h": 24,
	"Q_m3_s": 1473.66,
	"M_in_mg_L": 7,
	"Tage": 1,
	"Datum_Start": "25.05.2013",
	"mg_pro_24h": 7
},
{
	"PbTyp": "WASSER",
	"PbNahmeDatum": "26.05.2013",
	"Parameter": "Atrazin",
	"Einheiten": "µg/L",
	"Wert Text": 0.006,
	"CAS": "1912-24-9",
	"Gruppe": "Pestizide",
	"DauerPN_h": 24,
	"Q_m3_s": 1473.66,
	"M_in_mg_L": 6,
	"Tage": 1,
	"Datum_Start": "25.05.2013",
	"mg_pro_24h": 6
},
{
	"PbTyp": "WASSER",
	"PbNahmeDatum": "31.05.2013",
	"Parameter": "Atrazin",
	"Einheiten": "µg/L",
	"Wert Text": 0.006,
	"CAS": "1912-24-9",
	"Gruppe": "Pestizide",
	"DauerPN_h": 24,
	"Q_m3_s": 1677.52,
	"M_in_mg_L": 6,
	"Tage": 1,
	"Datum_Start": "30.05.2013",
	"mg_pro_24h": 6
},
{
	"PbTyp": "WASSER",
	"PbNahmeDatum": "01.06.2013",
	"Parameter": "Atrazin",
	"Einheiten": "µg/L",
	"Wert Text": 0.005,
	"CAS": "1912-24-9",
	"Gruppe": "Pestizide",
	"DauerPN_h": 24,
	"Q_m3_s": 2248.84,
	"M_in_mg_L": 5,
	"Tage": 1,
	"Datum_Start": "31.05.2013",
	"mg_pro_24h": 5
},
{
	"PbTyp": "WASSER",
	"PbNahmeDatum": "02.06.2013",
	"Parameter": "Atrazin",
	"Einheiten": "µg/L",
	"Wert Text": 0.005,
	"CAS": "1912-24-9",
	"Gruppe": "Pestizide",
	"DauerPN_h": 24,
	"Q_m3_s": 3678.85,
	"M_in_mg_L": 5,
	"Tage": 1,
	"Datum_Start": "01.06.2013",
	"mg_pro_24h": 5
},
{
	"PbTyp": "WASSER",
	"PbNahmeDatum": "03.06.2013",
	"Parameter": "Atrazin",
	"Einheiten": "µg/L",
	"Wert Text": 0.005,
	"CAS": "1912-24-9",
	"Gruppe": "Pestizide",
	"DauerPN_h": 24,
	"Q_m3_s": 3421.53,
	"M_in_mg_L": 5,
	"Tage": 1,
	"Datum_Start": "02.06.2013",
	"mg_pro_24h": 5
},
{
	"PbTyp": "WASSER",
	"PbNahmeDatum": "07.06.2013",
	"Parameter": "Atrazin",
	"Einheiten": "µg/L",
	"Wert Text": 0.005,
	"CAS": "1912-24-9",
	"Gruppe": "Pestizide",
	"DauerPN_h": 24,
	"Q_m3_s": 2355.11,
	"M_in_mg_L": 5,
	"Tage": 1,
	"Datum_Start": "06.06.2013",
	"mg_pro_24h": 5
},
{
	"PbTyp": "WASSER",
	"PbNahmeDatum": "11.06.2013",
	"Parameter": "Atrazin",
	"Einheiten": "µg/L",
	"Wert Text": 0.005,
	"CAS": "1912-24-9",
	"Gruppe": "Pestizide",
	"DauerPN_h": 24,
	"Q_m3_s": 2563.06,
	"M_in_mg_L": 5,
	"Tage": 1,
	"Datum_Start": "10.06.2013",
	"mg_pro_24h": 5
},
{
	"PbTyp": "WASSER",
	"PbNahmeDatum": "12.06.2013",
	"Parameter": "Atrazin",
	"Einheiten": "µg/L",
	"Wert Text": 0.006,
	"CAS": "1912-24-9",
	"Gruppe": "Pestizide",
	"DauerPN_h": 24,
	"Q_m3_s": 2400.3,
	"M_in_mg_L": 6,
	"Tage": 1,
	"Datum_Start": "11.06.2013",
	"mg_pro_24h": 6
},
{
	"PbTyp": "WASSER",
	"PbNahmeDatum": "14.06.2013",
	"Parameter": "Atrazin",
	"Einheiten": "µg/L",
	"Wert Text": 0.006,
	"CAS": "1912-24-9",
	"Gruppe": "Pestizide",
	"DauerPN_h": 24,
	"Q_m3_s": 2078.81,
	"M_in_mg_L": 6,
	"Tage": 1,
	"Datum_Start": "13.06.2013",
	"mg_pro_24h": 6
},
{
	"PbTyp": "WASSER",
	"PbNahmeDatum": "16.06.2013",
	"Parameter": "Atrazin",
	"Einheiten": "µg/L",
	"Wert Text": 0.006,
	"CAS": "1912-24-9",
	"Gruppe": "Pestizide",
	"DauerPN_h": 24,
	"Q_m3_s": 1898.2,
	"M_in_mg_L": 6,
	"Tage": 1,
	"Datum_Start": "15.06.2013",
	"mg_pro_24h": 6
},
{
	"PbTyp": "WASSER",
	"PbNahmeDatum": "17.06.2013",
	"Parameter": "Atrazin",
	"Einheiten": "µg/L",
	"Wert Text": 0.005,
	"CAS": "1912-24-9",
	"Gruppe": "Pestizide",
	"DauerPN_h": 24,
	"Q_m3_s": 1849.03,
	"M_in_mg_L": 5,
	"Tage": 1,
	"Datum_Start": "16.06.2013",
	"mg_pro_24h": 5
},
{
	"PbTyp": "WASSER",
	"PbNahmeDatum": "18.06.2013",
	"Parameter": "Atrazin",
	"Einheiten": "µg/L",
	"Wert Text": 0.006,
	"CAS": "1912-24-9",
	"Gruppe": "Pestizide",
	"DauerPN_h": 24,
	"Q_m3_s": 1883.95,
	"M_in_mg_L": 6,
	"Tage": 1,
	"Datum_Start": "17.06.2013",
	"mg_pro_24h": 6
},
{
	"PbTyp": "WASSER",
	"PbNahmeDatum": "05.07.2013",
	"Parameter": "Atrazin",
	"Einheiten": "µg/L",
	"Wert Text": 0.006,
	"CAS": "1912-24-9",
	"Gruppe": "Pestizide",
	"DauerPN_h": 24,
	"Q_m3_s": 1783.69,
	"M_in_mg_L": 6,
	"Tage": 1,
	"Datum_Start": "04.07.2013",
	"mg_pro_24h": 6
},
{
	"PbTyp": "WASSER",
	"PbNahmeDatum": "05.07.2013",
	"Parameter": "Atrazin",
	"Einheiten": "µg/L",
	"Wert Text": 0.005,
	"CAS": "1912-24-9",
	"Gruppe": "Pestizide",
	"DauerPN_h": 24,
	"Q_m3_s": 1783.69,
	"M_in_mg_L": 5,
	"Tage": 1,
	"Datum_Start": "04.07.2013",
	"mg_pro_24h": 5
},
{
	"PbTyp": "WASSER",
	"PbNahmeDatum": "06.07.2013",
	"Parameter": "Atrazin",
	"Einheiten": "µg/L",
	"Wert Text": 0.005,
	"CAS": "1912-24-9",
	"Gruppe": "Pestizide",
	"DauerPN_h": 24,
	"Q_m3_s": 1658.45,
	"M_in_mg_L": 5,
	"Tage": 1,
	"Datum_Start": "05.07.2013",
	"mg_pro_24h": 5
},
{
	"PbTyp": "WASSER",
	"PbNahmeDatum": "12.07.2013",
	"Parameter": "Atrazin",
	"Einheiten": "µg/L",
	"Wert Text": 0.005,
	"CAS": "1912-24-9",
	"Gruppe": "Pestizide",
	"DauerPN_h": 24,
	"Q_m3_s": 1406.06,
	"M_in_mg_L": 5,
	"Tage": 1,
	"Datum_Start": "11.07.2013",
	"mg_pro_24h": 5
},
{
	"PbTyp": "WASSER",
	"PbNahmeDatum": "25.07.2013",
	"Parameter": "Atrazin",
	"Einheiten": "µg/L",
	"Wert Text": 0.005,
	"CAS": "1912-24-9",
	"Gruppe": "Pestizide",
	"DauerPN_h": 24,
	"Q_m3_s": 1077.21,
	"M_in_mg_L": 5,
	"Tage": 1,
	"Datum_Start": "24.07.2013",
	"mg_pro_24h": 5
},
{
	"PbTyp": "WASSER",
	"PbNahmeDatum": "30.07.2013",
	"Parameter": "Atrazin",
	"Einheiten": "µg/L",
	"Wert Text": 0.005,
	"CAS": "1912-24-9",
	"Gruppe": "Pestizide",
	"DauerPN_h": 24,
	"Q_m3_s": 1591.67,
	"M_in_mg_L": 5,
	"Tage": 1,
	"Datum_Start": "29.07.2013",
	"mg_pro_24h": 5
},
{
	"PbTyp": "WASSER",
	"PbNahmeDatum": "01.08.2013",
	"Parameter": "Atrazin",
	"Einheiten": "µg/L",
	"Wert Text": 0.005,
	"CAS": "1912-24-9",
	"Gruppe": "Pestizide",
	"DauerPN_h": 24,
	"Q_m3_s": 1410.97,
	"M_in_mg_L": 5,
	"Tage": 1,
	"Datum_Start": "31.07.2013",
	"mg_pro_24h": 5
},
{
	"PbTyp": "WASSER",
	"PbNahmeDatum": "02.08.2013",
	"Parameter": "Atrazin",
	"Einheiten": "µg/L",
	"Wert Text": 0.005,
	"CAS": "1912-24-9",
	"Gruppe": "Pestizide",
	"DauerPN_h": 24,
	"Q_m3_s": 1258.59,
	"M_in_mg_L": 5,
	"Tage": 1,
	"Datum_Start": "01.08.2013",
	"mg_pro_24h": 5
},
{
	"PbTyp": "WASSER",
	"PbNahmeDatum": "03.08.2013",
	"Parameter": "Atrazin",
	"Einheiten": "µg/L",
	"Wert Text": 0.005,
	"CAS": "1912-24-9",
	"Gruppe": "Pestizide",
	"DauerPN_h": 24,
	"Q_m3_s": 1168.08,
	"M_in_mg_L": 5,
	"Tage": 1,
	"Datum_Start": "02.08.2013",
	"mg_pro_24h": 5
},
{
	"PbTyp": "WASSER",
	"PbNahmeDatum": "08.08.2013",
	"Parameter": "Atrazin",
	"Einheiten": "µg/L",
	"Wert Text": 0.005,
	"CAS": "1912-24-9",
	"Gruppe": "Pestizide",
	"DauerPN_h": 24,
	"Q_m3_s": 1113.76,
	"M_in_mg_L": 5,
	"Tage": 1,
	"Datum_Start": "07.08.2013",
	"mg_pro_24h": 5
},
{
	"PbTyp": "WASSER",
	"PbNahmeDatum": "09.08.2013",
	"Parameter": "Atrazin",
	"Einheiten": "µg/L",
	"Wert Text": 0.006,
	"CAS": "1912-24-9",
	"Gruppe": "Pestizide",
	"DauerPN_h": 24,
	"Q_m3_s": 1121.37,
	"M_in_mg_L": 6,
	"Tage": 1,
	"Datum_Start": "08.08.2013",
	"mg_pro_24h": 6
},
{
	"PbTyp": "WASSER",
	"PbNahmeDatum": "10.08.2013",
	"Parameter": "Atrazin",
	"Einheiten": "µg/L",
	"Wert Text": 0.006,
	"CAS": "1912-24-9",
	"Gruppe": "Pestizide",
	"DauerPN_h": 24,
	"Q_m3_s": 1206.53,
	"M_in_mg_L": 6,
	"Tage": 1,
	"Datum_Start": "09.08.2013",
	"mg_pro_24h": 6
},
{
	"PbTyp": "WASSER",
	"PbNahmeDatum": "17.08.2013",
	"Parameter": "Atrazin",
	"Einheiten": "µg/L",
	"Wert Text": 0.007,
	"CAS": "1912-24-9",
	"Gruppe": "Pestizide",
	"DauerPN_h": 24,
	"Q_m3_s": 827.81,
	"M_in_mg_L": 7,
	"Tage": 1,
	"Datum_Start": "16.08.2013",
	"mg_pro_24h": 7
},
{
	"PbTyp": "WASSER",
	"PbNahmeDatum": "17.08.2013",
	"Parameter": "Atrazin",
	"Einheiten": "µg/L",
	"Wert Text": 0.006,
	"CAS": "1912-24-9",
	"Gruppe": "Pestizide",
	"DauerPN_h": 24,
	"Q_m3_s": 827.81,
	"M_in_mg_L": 6,
	"Tage": 1,
	"Datum_Start": "16.08.2013",
	"mg_pro_24h": 6
},
{
	"PbTyp": "WASSER",
	"PbNahmeDatum": "22.08.2013",
	"Parameter": "Atrazin",
	"Einheiten": "µg/L",
	"Wert Text": 0.005,
	"CAS": "1912-24-9",
	"Gruppe": "Pestizide",
	"DauerPN_h": 24,
	"Q_m3_s": 757.23,
	"M_in_mg_L": 5,
	"Tage": 1,
	"Datum_Start": "21.08.2013",
	"mg_pro_24h": 5
},
{
	"PbTyp": "WASSER",
	"PbNahmeDatum": "23.08.2013",
	"Parameter": "Atrazin",
	"Einheiten": "µg/L",
	"Wert Text": 0.005,
	"CAS": "1912-24-9",
	"Gruppe": "Pestizide",
	"DauerPN_h": 24,
	"Q_m3_s": 749.74,
	"M_in_mg_L": 5,
	"Tage": 1,
	"Datum_Start": "22.08.2013",
	"mg_pro_24h": 5
},
{
	"PbTyp": "WASSER",
	"PbNahmeDatum": "07.09.2013",
	"Parameter": "Atrazin",
	"Einheiten": "µg/L",
	"Wert Text": 0.005,
	"CAS": "1912-24-9",
	"Gruppe": "Pestizide",
	"DauerPN_h": 24,
	"Q_m3_s": 639.45,
	"M_in_mg_L": 5,
	"Tage": 1,
	"Datum_Start": "06.09.2013",
	"mg_pro_24h": 5
},
{
	"PbTyp": "WASSER",
	"PbNahmeDatum": "10.09.2013",
	"Parameter": "Atrazin",
	"Einheiten": "µg/L",
	"Wert Text": 0.005,
	"CAS": "1912-24-9",
	"Gruppe": "Pestizide",
	"DauerPN_h": 24,
	"Q_m3_s": 803.71,
	"M_in_mg_L": 5,
	"Tage": 1,
	"Datum_Start": "09.09.2013",
	"mg_pro_24h": 5
},
{
	"PbTyp": "WASSER",
	"PbNahmeDatum": "11.09.2013",
	"Parameter": "Atrazin",
	"Einheiten": "µg/L",
	"Wert Text": 0.005,
	"CAS": "1912-24-9",
	"Gruppe": "Pestizide",
	"DauerPN_h": 24,
	"Q_m3_s": 799.4,
	"M_in_mg_L": 5,
	"Tage": 1,
	"Datum_Start": "10.09.2013",
	"mg_pro_24h": 5
},
{
	"PbTyp": "WASSER",
	"PbNahmeDatum": "18.09.2013",
	"Parameter": "Atrazin",
	"Einheiten": "µg/L",
	"Wert Text": 0.005,
	"CAS": "1912-24-9",
	"Gruppe": "Pestizide",
	"DauerPN_h": 24,
	"Q_m3_s": 1340.41,
	"M_in_mg_L": 5,
	"Tage": 1,
	"Datum_Start": "17.09.2013",
	"mg_pro_24h": 5
},
{
	"PbTyp": "WASSER",
	"PbNahmeDatum": "19.09.2013",
	"Parameter": "Atrazin",
	"Einheiten": "µg/L",
	"Wert Text": 0.012,
	"CAS": "1912-24-9",
	"Gruppe": "Pestizide",
	"DauerPN_h": 24,
	"Q_m3_s": 1475.61,
	"M_in_mg_L": 12,
	"Tage": 1,
	"Datum_Start": "18.09.2013",
	"mg_pro_24h": 12
},
{
	"PbTyp": "WASSER",
	"PbNahmeDatum": "19.09.2013",
	"Parameter": "Atrazin",
	"Einheiten": "µg/L",
	"Wert Text": 0.011,
	"CAS": "1912-24-9",
	"Gruppe": "Pestizide",
	"DauerPN_h": 24,
	"Q_m3_s": 1475.61,
	"M_in_mg_L": 11,
	"Tage": 1,
	"Datum_Start": "18.09.2013",
	"mg_pro_24h": 11
},
{
	"PbTyp": "WASSER",
	"PbNahmeDatum": "20.09.2013",
	"Parameter": "Atrazin",
	"Einheiten": "µg/L",
	"Wert Text": 0.006,
	"CAS": "1912-24-9",
	"Gruppe": "Pestizide",
	"DauerPN_h": 24,
	"Q_m3_s": 1772.02,
	"M_in_mg_L": 6,
	"Tage": 1,
	"Datum_Start": "19.09.2013",
	"mg_pro_24h": 6
},
{
	"PbTyp": "WASSER",
	"PbNahmeDatum": "13.10.2013",
	"Parameter": "Atrazin",
	"Einheiten": "µg/L",
	"Wert Text": 0.006,
	"CAS": "1912-24-9",
	"Gruppe": "Pestizide",
	"DauerPN_h": 24,
	"Q_m3_s": 958.85,
	"M_in_mg_L": 6,
	"Tage": 1,
	"Datum_Start": "12.10.2013",
	"mg_pro_24h": 6
},
{
	"PbTyp": "WASSER",
	"PbNahmeDatum": "14.10.2013",
	"Parameter": "Atrazin",
	"Einheiten": "µg/L",
	"Wert Text": 0.006,
	"CAS": "1912-24-9",
	"Gruppe": "Pestizide",
	"DauerPN_h": 24,
	"Q_m3_s": 946.46,
	"M_in_mg_L": 6,
	"Tage": 1,
	"Datum_Start": "13.10.2013",
	"mg_pro_24h": 6
},
{
	"PbTyp": "WASSER",
	"PbNahmeDatum": "15.10.2013",
	"Parameter": "Atrazin",
	"Einheiten": "µg/L",
	"Wert Text": 0.005,
	"CAS": "1912-24-9",
	"Gruppe": "Pestizide",
	"DauerPN_h": 24,
	"Q_m3_s": 966.22,
	"M_in_mg_L": 5,
	"Tage": 1,
	"Datum_Start": "14.10.2013",
	"mg_pro_24h": 5
},
{
	"PbTyp": "WASSER",
	"PbNahmeDatum": "16.10.2013",
	"Parameter": "Atrazin",
	"Einheiten": "µg/L",
	"Wert Text": 0.005,
	"CAS": "1912-24-9",
	"Gruppe": "Pestizide",
	"DauerPN_h": 24,
	"Q_m3_s": 1048.61,
	"M_in_mg_L": 5,
	"Tage": 1,
	"Datum_Start": "15.10.2013",
	"mg_pro_24h": 5
},
{
	"PbTyp": "WASSER",
	"PbNahmeDatum": "17.10.2013",
	"Parameter": "Atrazin",
	"Einheiten": "µg/L",
	"Wert Text": 0.006,
	"CAS": "1912-24-9",
	"Gruppe": "Pestizide",
	"DauerPN_h": 24,
	"Q_m3_s": 1443.11,
	"M_in_mg_L": 6,
	"Tage": 1,
	"Datum_Start": "16.10.2013",
	"mg_pro_24h": 6
},
{
	"PbTyp": "WASSER",
	"PbNahmeDatum": "26.10.2013",
	"Parameter": "Atrazin",
	"Einheiten": "µg/L",
	"Wert Text": 0.005,
	"CAS": "1912-24-9",
	"Gruppe": "Pestizide",
	"DauerPN_h": 24,
	"Q_m3_s": 992.75,
	"M_in_mg_L": 5,
	"Tage": 1,
	"Datum_Start": "25.10.2013",
	"mg_pro_24h": 5
},
{
	"PbTyp": "WASSER",
	"PbNahmeDatum": "27.10.2013",
	"Parameter": "Atrazin",
	"Einheiten": "µg/L",
	"Wert Text": 0.006,
	"CAS": "1912-24-9",
	"Gruppe": "Pestizide",
	"DauerPN_h": 24,
	"Q_m3_s": 983.26,
	"M_in_mg_L": 6,
	"Tage": 1,
	"Datum_Start": "26.10.2013",
	"mg_pro_24h": 6
},
{
	"PbTyp": "WASSER",
	"PbNahmeDatum": "28.10.2013",
	"Parameter": "Atrazin",
	"Einheiten": "µg/L",
	"Wert Text": 0.006,
	"CAS": "1912-24-9",
	"Gruppe": "Pestizide",
	"DauerPN_h": 24,
	"Q_m3_s": 1102.02,
	"M_in_mg_L": 6,
	"Tage": 1,
	"Datum_Start": "27.10.2013",
	"mg_pro_24h": 6
},
{
	"PbTyp": "WASSER",
	"PbNahmeDatum": "31.10.2013",
	"Parameter": "Atrazin",
	"Einheiten": "µg/L",
	"Wert Text": 0.005,
	"CAS": "1912-24-9",
	"Gruppe": "Pestizide",
	"DauerPN_h": 24,
	"Q_m3_s": 1115.98,
	"M_in_mg_L": 5,
	"Tage": 1,
	"Datum_Start": "30.10.2013",
	"mg_pro_24h": 5
},
{
	"PbTyp": "WASSER",
	"PbNahmeDatum": "03.11.2013",
	"Parameter": "Atrazin",
	"Einheiten": "µg/L",
	"Wert Text": 0.006,
	"CAS": "1912-24-9",
	"Gruppe": "Pestizide",
	"DauerPN_h": 24,
	"Q_m3_s": 1059.64,
	"M_in_mg_L": 6,
	"Tage": 1,
	"Datum_Start": "02.11.2013",
	"mg_pro_24h": 6
},
{
	"PbTyp": "WASSER",
	"PbNahmeDatum": "04.11.2013",
	"Parameter": "Atrazin",
	"Einheiten": "µg/L",
	"Wert Text": 0.005,
	"CAS": "1912-24-9",
	"Gruppe": "Pestizide",
	"DauerPN_h": 24,
	"Q_m3_s": 1561.1,
	"M_in_mg_L": 5,
	"Tage": 1,
	"Datum_Start": "03.11.2013",
	"mg_pro_24h": 5
},
{
	"PbTyp": "WASSER",
	"PbNahmeDatum": "06.11.2013",
	"Parameter": "Atrazin",
	"Einheiten": "µg/L",
	"Wert Text": 0.006,
	"CAS": "1912-24-9",
	"Gruppe": "Pestizide",
	"DauerPN_h": 24,
	"Q_m3_s": 1591.42,
	"M_in_mg_L": 6,
	"Tage": 1,
	"Datum_Start": "05.11.2013",
	"mg_pro_24h": 6
},
{
	"PbTyp": "WASSER",
	"PbNahmeDatum": "07.11.2013",
	"Parameter": "Atrazin",
	"Einheiten": "µg/L",
	"Wert Text": 0.006,
	"CAS": "1912-24-9",
	"Gruppe": "Pestizide",
	"DauerPN_h": 24,
	"Q_m3_s": 1817.64,
	"M_in_mg_L": 6,
	"Tage": 1,
	"Datum_Start": "06.11.2013",
	"mg_pro_24h": 6
},
{
	"PbTyp": "WASSER",
	"PbNahmeDatum": "09.11.2013",
	"Parameter": "Atrazin",
	"Einheiten": "µg/L",
	"Wert Text": 0.005,
	"CAS": "1912-24-9",
	"Gruppe": "Pestizide",
	"DauerPN_h": 24,
	"Q_m3_s": 1539.19,
	"M_in_mg_L": 5,
	"Tage": 1,
	"Datum_Start": "08.11.2013",
	"mg_pro_24h": 5
},
{
	"PbTyp": "WASSER",
	"PbNahmeDatum": "10.11.2013",
	"Parameter": "Atrazin",
	"Einheiten": "µg/L",
	"Wert Text": 0.006,
	"CAS": "1912-24-9",
	"Gruppe": "Pestizide",
	"DauerPN_h": 24,
	"Q_m3_s": 1600.33,
	"M_in_mg_L": 6,
	"Tage": 1,
	"Datum_Start": "09.11.2013",
	"mg_pro_24h": 6
},
{
	"PbTyp": "WASSER",
	"PbNahmeDatum": "12.11.2013",
	"Parameter": "Atrazin",
	"Einheiten": "µg/L",
	"Wert Text": 0.006,
	"CAS": "1912-24-9",
	"Gruppe": "Pestizide",
	"DauerPN_h": 24,
	"Q_m3_s": 1736.25,
	"M_in_mg_L": 6,
	"Tage": 1,
	"Datum_Start": "11.11.2013",
	"mg_pro_24h": 6
},
{
	"PbTyp": "WASSER",
	"PbNahmeDatum": "14.11.2013",
	"Parameter": "Atrazin",
	"Einheiten": "µg/L",
	"Wert Text": 0.006,
	"CAS": "1912-24-9",
	"Gruppe": "Pestizide",
	"DauerPN_h": 24,
	"Q_m3_s": 1503.03,
	"M_in_mg_L": 6,
	"Tage": 1,
	"Datum_Start": "13.11.2013",
	"mg_pro_24h": 6
},
{
	"PbTyp": "WASSER",
	"PbNahmeDatum": "16.11.2013",
	"Parameter": "Atrazin",
	"Einheiten": "µg/L",
	"Wert Text": 0.006,
	"CAS": "1912-24-9",
	"Gruppe": "Pestizide",
	"DauerPN_h": 24,
	"Q_m3_s": 1355.85,
	"M_in_mg_L": 6,
	"Tage": 1,
	"Datum_Start": "15.11.2013",
	"mg_pro_24h": 6
},
{
	"PbTyp": "WASSER",
	"PbNahmeDatum": "17.11.2013",
	"Parameter": "Atrazin",
	"Einheiten": "µg/L",
	"Wert Text": 0.006,
	"CAS": "1912-24-9",
	"Gruppe": "Pestizide",
	"DauerPN_h": 24,
	"Q_m3_s": 1150.2,
	"M_in_mg_L": 6,
	"Tage": 1,
	"Datum_Start": "16.11.2013",
	"mg_pro_24h": 6
},
{
	"PbTyp": "WASSER",
	"PbNahmeDatum": "18.11.2013",
	"Parameter": "Atrazin",
	"Einheiten": "µg/L",
	"Wert Text": 0.006,
	"CAS": "1912-24-9",
	"Gruppe": "Pestizide",
	"DauerPN_h": 24,
	"Q_m3_s": 1107.03,
	"M_in_mg_L": 6,
	"Tage": 1,
	"Datum_Start": "17.11.2013",
	"mg_pro_24h": 6
},
{
	"PbTyp": "WASSER",
	"PbNahmeDatum": "19.11.2013",
	"Parameter": "Atrazin",
	"Einheiten": "µg/L",
	"Wert Text": 0.005,
	"CAS": "1912-24-9",
	"Gruppe": "Pestizide",
	"DauerPN_h": 24,
	"Q_m3_s": 1109.4,
	"M_in_mg_L": 5,
	"Tage": 1,
	"Datum_Start": "18.11.2013",
	"mg_pro_24h": 5
},
{
	"PbTyp": "WASSER",
	"PbNahmeDatum": "20.11.2013",
	"Parameter": "Atrazin",
	"Einheiten": "µg/L",
	"Wert Text": 0.006,
	"CAS": "1912-24-9",
	"Gruppe": "Pestizide",
	"DauerPN_h": 24,
	"Q_m3_s": 1090.5,
	"M_in_mg_L": 6,
	"Tage": 1,
	"Datum_Start": "19.11.2013",
	"mg_pro_24h": 6
},
{
	"PbTyp": "WASSER",
	"PbNahmeDatum": "23.11.2013",
	"Parameter": "Atrazin",
	"Einheiten": "µg/L",
	"Wert Text": 0.005,
	"CAS": "1912-24-9",
	"Gruppe": "Pestizide",
	"DauerPN_h": 24,
	"Q_m3_s": 1091.88,
	"M_in_mg_L": 5,
	"Tage": 1,
	"Datum_Start": "22.11.2013",
	"mg_pro_24h": 5
},
{
	"PbTyp": "WASSER",
	"PbNahmeDatum": "25.11.2013",
	"Parameter": "Atrazin",
	"Einheiten": "µg/L",
	"Wert Text": 0.005,
	"CAS": "1912-24-9",
	"Gruppe": "Pestizide",
	"DauerPN_h": 24,
	"Q_m3_s": 1193.58,
	"M_in_mg_L": 5,
	"Tage": 1,
	"Datum_Start": "24.11.2013",
	"mg_pro_24h": 5
},
{
	"PbTyp": "WASSER",
	"PbNahmeDatum": "29.11.2013",
	"Parameter": "Atrazin",
	"Einheiten": "µg/L",
	"Wert Text": 0.005,
	"CAS": "1912-24-9",
	"Gruppe": "Pestizide",
	"DauerPN_h": 24,
	"Q_m3_s": 911.49,
	"M_in_mg_L": 5,
	"Tage": 1,
	"Datum_Start": "28.11.2013",
	"mg_pro_24h": 5
},
{
	"PbTyp": "WASSER",
	"PbNahmeDatum": "30.11.2013",
	"Parameter": "Atrazin",
	"Einheiten": "µg/L",
	"Wert Text": 0.005,
	"CAS": "1912-24-9",
	"Gruppe": "Pestizide",
	"DauerPN_h": 24,
	"Q_m3_s": 878.56,
	"M_in_mg_L": 5,
	"Tage": 1,
	"Datum_Start": "29.11.2013",
	"mg_pro_24h": 5
},
{
	"PbTyp": "WASSER",
	"PbNahmeDatum": "03.12.2013",
	"Parameter": "Atrazin",
	"Einheiten": "µg/L",
	"Wert Text": 0.005,
	"CAS": "1912-24-9",
	"Gruppe": "Pestizide",
	"DauerPN_h": 24,
	"Q_m3_s": 815.99,
	"M_in_mg_L": 5,
	"Tage": 1,
	"Datum_Start": "02.12.2013",
	"mg_pro_24h": 5
},
{
	"PbTyp": "WASSER",
	"PbNahmeDatum": "04.12.2013",
	"Parameter": "Atrazin",
	"Einheiten": "µg/L",
	"Wert Text": 0.006,
	"CAS": "1912-24-9",
	"Gruppe": "Pestizide",
	"DauerPN_h": 24,
	"Q_m3_s": 823.55,
	"M_in_mg_L": 6,
	"Tage": 1,
	"Datum_Start": "03.12.2013",
	"mg_pro_24h": 6
},
{
	"PbTyp": "WASSER",
	"PbNahmeDatum": "05.12.2013",
	"Parameter": "Atrazin",
	"Einheiten": "µg/L",
	"Wert Text": 0.005,
	"CAS": "1912-24-9",
	"Gruppe": "Pestizide",
	"DauerPN_h": 24,
	"Q_m3_s": 826.56,
	"M_in_mg_L": 5,
	"Tage": 1,
	"Datum_Start": "04.12.2013",
	"mg_pro_24h": 5
},
{
	"PbTyp": "WASSER",
	"PbNahmeDatum": "06.12.2013",
	"Parameter": "Atrazin",
	"Einheiten": "µg/L",
	"Wert Text": 0.006,
	"CAS": "1912-24-9",
	"Gruppe": "Pestizide",
	"DauerPN_h": 24,
	"Q_m3_s": 796.57,
	"M_in_mg_L": 6,
	"Tage": 1,
	"Datum_Start": "05.12.2013",
	"mg_pro_24h": 6
},
{
	"PbTyp": "WASSER",
	"PbNahmeDatum": "07.12.2013",
	"Parameter": "Atrazin",
	"Einheiten": "µg/L",
	"Wert Text": 0.006,
	"CAS": "1912-24-9",
	"Gruppe": "Pestizide",
	"DauerPN_h": 24,
	"Q_m3_s": 812.96,
	"M_in_mg_L": 6,
	"Tage": 1,
	"Datum_Start": "06.12.2013",
	"mg_pro_24h": 6
},
{
	"PbTyp": "WASSER",
	"PbNahmeDatum": "08.12.2013",
	"Parameter": "Atrazin",
	"Einheiten": "µg/L",
	"Wert Text": 0.005,
	"CAS": "1912-24-9",
	"Gruppe": "Pestizide",
	"DauerPN_h": 24,
	"Q_m3_s": 786.67,
	"M_in_mg_L": 5,
	"Tage": 1,
	"Datum_Start": "07.12.2013",
	"mg_pro_24h": 5
},
{
	"PbTyp": "WASSER",
	"PbNahmeDatum": "09.12.2013",
	"Parameter": "Atrazin",
	"Einheiten": "µg/L",
	"Wert Text": 0.005,
	"CAS": "1912-24-9",
	"Gruppe": "Pestizide",
	"DauerPN_h": 24,
	"Q_m3_s": 754.29,
	"M_in_mg_L": 5,
	"Tage": 1,
	"Datum_Start": "08.12.2013",
	"mg_pro_24h": 5
},
{
	"PbTyp": "WASSER",
	"PbNahmeDatum": "10.12.2013",
	"Parameter": "Atrazin",
	"Einheiten": "µg/L",
	"Wert Text": 0.006,
	"CAS": "1912-24-9",
	"Gruppe": "Pestizide",
	"DauerPN_h": 24,
	"Q_m3_s": 725.5,
	"M_in_mg_L": 6,
	"Tage": 1,
	"Datum_Start": "09.12.2013",
	"mg_pro_24h": 6
},
{
	"PbTyp": "WASSER",
	"PbNahmeDatum": "11.12.2013",
	"Parameter": "Atrazin",
	"Einheiten": "µg/L",
	"Wert Text": 0.006,
	"CAS": "1912-24-9",
	"Gruppe": "Pestizide",
	"DauerPN_h": 24,
	"Q_m3_s": 703.7,
	"M_in_mg_L": 6,
	"Tage": 1,
	"Datum_Start": "10.12.2013",
	"mg_pro_24h": 6
},
{
	"PbTyp": "WASSER",
	"PbNahmeDatum": "12.12.2013",
	"Parameter": "Atrazin",
	"Einheiten": "µg/L",
	"Wert Text": 0.005,
	"CAS": "1912-24-9",
	"Gruppe": "Pestizide",
	"DauerPN_h": 24,
	"Q_m3_s": 729.12,
	"M_in_mg_L": 5,
	"Tage": 1,
	"Datum_Start": "11.12.2013",
	"mg_pro_24h": 5
},
{
	"PbTyp": "WASSER",
	"PbNahmeDatum": "13.12.2013",
	"Parameter": "Atrazin",
	"Einheiten": "µg/L",
	"Wert Text": 0.005,
	"CAS": "1912-24-9",
	"Gruppe": "Pestizide",
	"DauerPN_h": 24,
	"Q_m3_s": 715.17,
	"M_in_mg_L": 5,
	"Tage": 1,
	"Datum_Start": "12.12.2013",
	"mg_pro_24h": 5
},
{
	"PbTyp": "WASSER",
	"PbNahmeDatum": "15.12.2013",
	"Parameter": "Atrazin",
	"Einheiten": "µg/L",
	"Wert Text": 0.005,
	"CAS": "1912-24-9",
	"Gruppe": "Pestizide",
	"DauerPN_h": 24,
	"Q_m3_s": 685.06,
	"M_in_mg_L": 5,
	"Tage": 1,
	"Datum_Start": "14.12.2013",
	"mg_pro_24h": 5
},
{
	"PbTyp": "WASSER",
	"PbNahmeDatum": "16.12.2013",
	"Parameter": "Atrazin",
	"Einheiten": "µg/L",
	"Wert Text": 0.007,
	"CAS": "1912-24-9",
	"Gruppe": "Pestizide",
	"DauerPN_h": 24,
	"Q_m3_s": 668.96,
	"M_in_mg_L": 7,
	"Tage": 1,
	"Datum_Start": "15.12.2013",
	"mg_pro_24h": 7
},
{
	"PbTyp": "WASSER",
	"PbNahmeDatum": "18.12.2013",
	"Parameter": "Atrazin",
	"Einheiten": "µg/L",
	"Wert Text": 0.005,
	"CAS": "1912-24-9",
	"Gruppe": "Pestizide",
	"DauerPN_h": 24,
	"Q_m3_s": 644.3,
	"M_in_mg_L": 5,
	"Tage": 1,
	"Datum_Start": "17.12.2013",
	"mg_pro_24h": 5
},
{
	"PbTyp": "WASSER",
	"PbNahmeDatum": "19.12.2013",
	"Parameter": "Atrazin",
	"Einheiten": "µg/L",
	"Wert Text": 0.005,
	"CAS": "1912-24-9",
	"Gruppe": "Pestizide",
	"DauerPN_h": 24,
	"Q_m3_s": 643.15,
	"M_in_mg_L": 5,
	"Tage": 1,
	"Datum_Start": "18.12.2013",
	"mg_pro_24h": 5
},
{
	"PbTyp": "WASSER",
	"PbNahmeDatum": "20.12.2013",
	"Parameter": "Atrazin",
	"Einheiten": "µg/L",
	"Wert Text": 0.006,
	"CAS": "1912-24-9",
	"Gruppe": "Pestizide",
	"DauerPN_h": 24,
	"Q_m3_s": 696.97,
	"M_in_mg_L": 6,
	"Tage": 1,
	"Datum_Start": "19.12.2013",
	"mg_pro_24h": 6
},
{
	"PbTyp": "WASSER",
	"PbNahmeDatum": "23.12.2013",
	"Parameter": "Atrazin",
	"Einheiten": "µg/L",
	"Wert Text": 0.006,
	"CAS": "1912-24-9",
	"Gruppe": "Pestizide",
	"DauerPN_h": 24,
	"Q_m3_s": 702.69,
	"M_in_mg_L": 6,
	"Tage": 1,
	"Datum_Start": "22.12.2013",
	"mg_pro_24h": 6
},
{
	"PbTyp": "WASSER",
	"PbNahmeDatum": "25.12.2013",
	"Parameter": "Atrazin",
	"Einheiten": "µg/L",
	"Wert Text": 0.006,
	"CAS": "1912-24-9",
	"Gruppe": "Pestizide",
	"DauerPN_h": 24,
	"Q_m3_s": 695.73,
	"M_in_mg_L": 6,
	"Tage": 1,
	"Datum_Start": "24.12.2013",
	"mg_pro_24h": 6
},
{
	"PbTyp": "WASSER",
	"PbNahmeDatum": "26.12.2013",
	"Parameter": "Atrazin",
	"Einheiten": "µg/L",
	"Wert Text": 0.006,
	"CAS": "1912-24-9",
	"Gruppe": "Pestizide",
	"DauerPN_h": 24,
	"Q_m3_s": 894,
	"M_in_mg_L": 6,
	"Tage": 1,
	"Datum_Start": "25.12.2013",
	"mg_pro_24h": 6
},
{
	"PbTyp": "WASSER",
	"PbNahmeDatum": "31.12.2013",
	"Parameter": "Atrazin",
	"Einheiten": "µg/L",
	"Wert Text": 0.005,
	"CAS": "1912-24-9",
	"Gruppe": "Pestizide",
	"DauerPN_h": 24,
	"Q_m3_s": 962.98,
	"M_in_mg_L": 5,
	"Tage": 1,
	"Datum_Start": "30.12.2013",
	"mg_pro_24h": 5
}
]
